{"atletas":{"100079":{"scout":{"DS":2,"FC":1,"FD":2,"FF":1,"FS":2},"apelido":"Zaracho","foto":"https://s.sde.globo.com/media/person_role/2023/03/31/photo_FORMATO_wjGLEpf.png","pontuacao":6.3,"posicao_id":4,"clube_id":282,"entrou_em_campo":true},"100084":{"scout":{"CA":1,"FC":3,"FT":1},"apelido":"Igor Gomes","foto":"https://s.sde.globo.com/media/person_role/2023/03/31/photo_FORMATO_UzfIqe6.png","pontuacao":1.1,"posicao_id":4,"clube_id":282,"entrou_em_campo":true},"100085":{"scout":{"CA":1,"DS":3,"FC":1,"FD":1,"FS":1},"apelido":"Pedro Augusto","foto":"https://s.sde.globo.com/media/person_role/2024/02/28/photo_FORMATO_omYwNQA.png","pontuacao":4,"posicao_id":4,"clube_id":356,"entrou_em_campo":true},"100652":{"scout":{"CA":1,"FC":1,"FD":1,"FF":1,"FS":1},"apelido":"Yuri Alberto","foto":"https://s.sde.globo.com/media/person_role/2024/02/27/photo_FORMATO_wt9arbZ.png","pontuacao":1.2,"posicao_id":5,"clube_id":264,"entrou_em_campo":true},"100846":{"scout":{},"apelido":"Lucas Esteves","foto":"https://s.sde.globo.com/media/person_role/2024/04/12/photo_FORMATO_Oqbbci1.png","pontuacao":0,"posicao_id":2,"clube_id":287,"entrou_em_campo":true},"100969":{"scout":{"DS":1,"FC":1,"FF":1},"apelido":"Ronald Lopes","foto":"https://s.sde.globo.com/media/person_role/2024/04/19/photo_FORMATO_Nhk7IV4.png","pontuacao":1.7,"posicao_id":4,"clube_id":288,"entrou_em_campo":true},"101002":{"scout":{"FC":1,"FD":1,"I":1},"apelido":"Júnior Santos","foto":"https://s.sde.globo.com/media/person_role/2024/04/20/photo_FORMATO_GZeQZHl.png","pontuacao":0.8,"posicao_id":5,"clube_id":263,"entrou_em_campo":true},"101290":{"scout":{"FS":1},"apelido":"Ferreira","foto":"https://s.sde.globo.com/media/person_role/2024/03/01/photo_FORMATO_nPg7koa.png","pontuacao":0.5,"posicao_id":5,"clube_id":276,"entrou_em_campo":true},"101314":{"scout":{"I":1},"apelido":"Ademir","foto":"https://s.sde.globo.com/media/person_role/2024/02/29/photo_FORMATO_IWREALz.png","pontuacao":-0.1,"posicao_id":5,"clube_id":265,"entrou_em_campo":true},"101431":{"scout":{"FF":2,"FS":2,"SG":1},"apelido":"Danilo Boza","foto":"https://s.sde.globo.com/media/person_role/2024/03/11/photo_FORMATO_b7q5w0V.png","pontuacao":7.6,"posicao_id":3,"clube_id":286,"entrou_em_campo":true},"101573":{"scout":{"CV":1,"FC":1,"FF":1,"FS":1},"apelido":"Pepê","foto":"https://s.sde.globo.com/media/person_role/2024/03/11/photo_FORMATO_eQw4wlK.png","pontuacao":-2,"posicao_id":4,"clube_id":284,"entrou_em_campo":true},"101597":{"scout":{"CA":1,"FC":2,"FS":1,"SG":1},"apelido":"Ramon","foto":"https://s.sde.globo.com/media/person_role/2024/02/29/photo_FORMATO_j3eOqDC.png","pontuacao":3.9,"posicao_id":2,"clube_id":1371,"entrou_em_campo":true},"101601":{"scout":{"CA":1,"FC":2,"FS":1},"apelido":"Caio Vinícius","foto":"https://s.sde.globo.com/media/person_role/2024/04/12/photo_FORMATO_fCg7WfQ.png","pontuacao":-1.1,"posicao_id":4,"clube_id":287,"entrou_em_campo":true},"101666":{"scout":{"DS":2,"FS":1},"apelido":"Rhaldney","foto":"https://s.sde.globo.com/media/person_role/2024/02/28/photo_FORMATO_VWBr2KD.png","pontuacao":2.9,"posicao_id":4,"clube_id":373,"entrou_em_campo":true},"101708":{"scout":{"FC":1,"FS":1,"SG":1},"apelido":"Felipe Jonatan","foto":"https://s.sde.globo.com/media/person_role/2024/04/19/photo_FORMATO_ZDljmkA.png","pontuacao":5.2,"posicao_id":2,"clube_id":356,"entrou_em_campo":true},"101715":{"scout":{"DS":1,"FC":1,"FF":1,"FS":1},"apelido":"Alerrandro","foto":"https://s.sde.globo.com/media/person_role/2024/04/12/photo_FORMATO_v6x7rRS.png","pontuacao":2.2,"posicao_id":5,"clube_id":287,"entrou_em_campo":true},"101726":{"scout":{"A":1,"CA":1,"FC":2,"SG":1},"apelido":"Railan","foto":"https://s.sde.globo.com/media/person_role/2024/02/29/photo_FORMATO_glaRaXf.png","pontuacao":8.4,"posicao_id":2,"clube_id":1371,"entrou_em_campo":true},"101727":{"scout":{"DS":4,"FC":1},"apelido":"Matheuzinho","foto":"https://s.sde.globo.com/media/person_role/2024/02/27/photo_FORMATO_Mq6sxK4.png","pontuacao":4.5,"posicao_id":2,"clube_id":264,"entrou_em_campo":true},"101728":{"scout":{"DS":1,"FC":1,"FD":1},"apelido":"Diego Costa","foto":"https://s.sde.globo.com/media/person_role/2024/03/01/photo_FORMATO_ApqbX2X.png","pontuacao":2.1,"posicao_id":3,"clube_id":276,"entrou_em_campo":true},"101752":{"scout":{},"apelido":"Claudinho","foto":"https://s.sde.globo.com/media/person_role/2024/01/16/photo_FORMATO_6lSysiX.png","pontuacao":0,"posicao_id":2,"clube_id":288,"entrou_em_campo":true},"101960":{"scout":{"CA":1,"FC":2},"apelido":"Vitinho","foto":"https://s.sde.globo.com/media/person_role/2024/01/03/photo_FORMATO_fcyTaPY.png","pontuacao":-1.6,"posicao_id":5,"clube_id":280,"entrou_em_campo":true},"102130":{"scout":{"DS":3,"FD":1,"FF":1,"FS":1},"apelido":"Piquerez","foto":"https://s.sde.globo.com/media/person_role/2024/02/27/photo_FORMATO_loXGEPe.png","pontuacao":6.1,"posicao_id":2,"clube_id":275,"entrou_em_campo":true},"102253":{"scout":{"FC":2,"FF":1,"FS":1},"apelido":"Lucas Halter","foto":"https://s.sde.globo.com/media/person_role/2024/04/20/photo_FORMATO_SVv6kJE.png","pontuacao":0.7,"posicao_id":3,"clube_id":263,"entrou_em_campo":true},"102340":{"scout":{"DS":1,"FC":2,"FF":1,"FS":3},"apelido":"Cacá","foto":"https://s.sde.globo.com/media/person_role/2024/03/07/photo_FORMATO.png","pontuacao":2.9,"posicao_id":3,"clube_id":264,"entrou_em_campo":true},"102561":{"scout":{"DS":1,"FC":2,"FS":1,"G":1,"I":1},"apelido":"Mastriani","foto":"https://s.sde.globo.com/media/person_role/2024/03/05/photo_FORMATO_JrvZkOm.png","pontuacao":9,"posicao_id":5,"clube_id":293,"entrou_em_campo":true},"102598":{"scout":{"DS":1,"FC":1,"FD":1,"FF":3},"apelido":"Helinho","foto":"https://s.sde.globo.com/media/person_role/2024/01/03/photo_FORMATO_HKFN5Du.png","pontuacao":4.5,"posicao_id":5,"clube_id":280,"entrou_em_campo":true},"102796":{"scout":{"FC":2},"apelido":"Julimar","foto":"https://s.sde.globo.com/media/person_role/2024/03/04/photo_FORMATO_do5hHhP.png","pontuacao":-0.6,"posicao_id":5,"clube_id":293,"entrou_em_campo":true},"102878":{"scout":{"FC":1,"FD":1},"apelido":"Terans","foto":"https://s.sde.globo.com/media/person_role/2024/04/09/photo_FORMATO_hfdtfwn.png","pontuacao":0.9,"posicao_id":4,"clube_id":266,"entrou_em_campo":true},"102906":{"scout":{"DE":4,"SG":1},"apelido":"Anderson","foto":"https://s.sde.globo.com/media/person_role/2024/03/01/photo_FORMATO_pMtI9RP.png","pontuacao":9,"posicao_id":1,"clube_id":283,"entrou_em_campo":true},"102909":{"scout":{"CA":1,"DS":1,"FC":1},"apelido":"Luan Vinícius","foto":"https://s.sde.globo.com/media/person_role/2024/04/12/photo_FORMATO_Zd7I4CW.png","pontuacao":-0.1,"posicao_id":4,"clube_id":287,"entrou_em_campo":true},"103014":{"scout":{},"apelido":"Laquintana","foto":"https://s.sde.globo.com/media/person_role/2024/01/03/photo_FORMATO_lsx86RT.png","pontuacao":0,"posicao_id":5,"clube_id":280,"entrou_em_campo":true},"103295":{"scout":{"CA":1,"FF":1},"apelido":"Eric Ramires","foto":"https://s.sde.globo.com/media/person_role/2024/01/03/photo_FORMATO_3VHcc20.png","pontuacao":-0.2,"posicao_id":4,"clube_id":280,"entrou_em_campo":true},"103347":{"scout":{"DS":2,"FC":1,"FF":1,"SG":1},"apelido":"Matheus Alexandre","foto":"https://s.sde.globo.com/media/person_role/2024/02/29/photo_FORMATO_V7nD4iR.png","pontuacao":7.9,"posicao_id":2,"clube_id":1371,"entrou_em_campo":true},"103388":{"scout":{"DS":3,"FF":1,"FS":1,"FT":1},"apelido":"Emmanuel Martínez","foto":"https://s.sde.globo.com/media/person_role/2024/06/14/photo_FORMATO.png","pontuacao":7.9,"posicao_id":4,"clube_id":356,"entrou_em_campo":true},"103684":{"scout":{"DS":1},"apelido":"Kaíque Rocha","foto":"https://s.sde.globo.com/media/person_role/2024/03/04/photo_FORMATO_1ebxa2m.png","pontuacao":1.2,"posicao_id":3,"clube_id":293,"entrou_em_campo":true},"103764":{"scout":{"FC":1,"FD":1},"apelido":"Gabriel Veron","foto":"https://s.sde.globo.com/media/person_role/2024/03/01/photo_FORMATO_Kh2CeQC.png","pontuacao":0.9,"posicao_id":5,"clube_id":283,"entrou_em_campo":true},"103767":{"scout":{"DS":1,"FC":3,"FD":1,"FF":1,"FS":1,"I":1},"apelido":"Gabriel Menino","foto":"https://s.sde.globo.com/media/person_role/2024/02/27/photo_FORMATO_yzWSMvb.png","pontuacao":2.7,"posicao_id":4,"clube_id":275,"entrou_em_campo":true},"103987":{"scout":{"FC":1,"FD":1},"apelido":"Higor Meritão","foto":"https://s.sde.globo.com/media/person_role/2024/03/25/photo_FORMATO_5y8FTJb.png","pontuacao":0.9,"posicao_id":4,"clube_id":288,"entrou_em_campo":true},"104085":{"scout":{"DS":3,"FC":1,"FS":1},"apelido":"Bruno Fuchs","foto":"https://s.sde.globo.com/media/person_role/2024/03/06/photo_FORMATO_6xGko1v.png","pontuacao":3.8,"posicao_id":3,"clube_id":282,"entrou_em_campo":true},"104118":{"scout":{"DE":5,"GS":2},"apelido":"Lucas Arcanjo","foto":"https://s.sde.globo.com/media/person_role/2024/04/12/photo_FORMATO_0iYWFXU.png","pontuacao":3,"posicao_id":1,"clube_id":287,"entrou_em_campo":true},"104257":{"scout":{"DS":2,"FC":2,"FS":1,"SG":1},"apelido":"João Lucas","foto":"https://s.sde.globo.com/media/person_role/2024/03/11/photo_FORMATO_Ey1s4jw.png","pontuacao":7.3,"posicao_id":2,"clube_id":286,"entrou_em_campo":true},"104276":{"scout":{"DS":2,"FC":1,"FS":2},"apelido":"Calegari","foto":"https://s.sde.globo.com/media/person_role/2024/04/09/photo_FORMATO_YfMFo2m.png","pontuacao":3.1,"posicao_id":2,"clube_id":266,"entrou_em_campo":true},"104385":{"scout":{"A":1,"DS":2,"FS":1,"SG":1},"apelido":"Igor Gomes","foto":"https://s.sde.globo.com/media/person_role/2024/03/01/photo_FORMATO_mxuErJK.png","pontuacao":12.9,"posicao_id":3,"clube_id":285,"entrou_em_campo":true},"104502":{"scout":{"CA":1,"DS":1,"FC":2,"FD":1,"I":1},"apelido":"Christian","foto":"https://s.sde.globo.com/media/person_role/2024/03/01/photo_FORMATO_4ASqaCm.png","pontuacao":0.7,"posicao_id":4,"clube_id":293,"entrou_em_campo":true},"104693":{"scout":{"DS":1,"FF":2,"G":1},"apelido":"Newton","foto":"https://s.sde.globo.com/media/person_role/2024/04/19/photo_FORMATO_TFHsgGX.png","pontuacao":10.8,"posicao_id":4,"clube_id":288,"entrou_em_campo":true},"104754":{"scout":{"V":1},"apelido":"Juan Vojvoda","foto":"https://s.sde.globo.com/media/person_role/2023/03/07/photo_FORMATO_UIx1Yzg.png","pontuacao":6.66,"posicao_id":6,"clube_id":356,"entrou_em_campo":true},"104759":{"scout":{"DS":3,"FC":1,"FF":1},"apelido":"Leo Godoy","foto":"https://s.sde.globo.com/media/person_role/2024/01/19/photo_FORMATO.png","pontuacao":4.1,"posicao_id":2,"clube_id":293,"entrou_em_campo":true},"104994":{"scout":{"DS":1},"apelido":"Wagner Leonardo","foto":"https://s.sde.globo.com/media/person_role/2024/04/12/photo_FORMATO_kfLtGgD.png","pontuacao":1.2,"posicao_id":3,"clube_id":287,"entrou_em_campo":true},"105047":{"scout":{"FD":1,"FF":1,"SG":1},"apelido":"João Marcelo","foto":"https://s.sde.globo.com/media/person_role/2024/03/01/photo_FORMATO_s2GXfyO.png","pontuacao":7,"posicao_id":3,"clube_id":283,"entrou_em_campo":true},"105373":{"scout":{"DS":1},"apelido":"Gabriel Xavier","foto":"https://s.sde.globo.com/media/person_role/2024/02/29/photo_FORMATO_7TSdotN.png","pontuacao":1.2,"posicao_id":3,"clube_id":265,"entrou_em_campo":true},"105531":{"scout":{"FC":1,"FS":2},"apelido":"Matheus Bidu","foto":"https://s.sde.globo.com/media/person_role/2024/02/27/photo_FORMATO_1Zas2lO.png","pontuacao":0.7,"posicao_id":2,"clube_id":264,"entrou_em_campo":true},"105547":{"scout":{"SG":1},"apelido":"Rikelme","foto":"https://s.sde.globo.com/media/person_role/2024/02/29/photo_FORMATO_GWnqoHo.png","pontuacao":5,"posicao_id":2,"clube_id":1371,"entrou_em_campo":true},"105568":{"scout":{"CA":1,"DS":1,"FC":3,"FD":1,"FF":2,"G":1},"apelido":"Lucero","foto":"https://s.sde.globo.com/media/person_role/2024/02/28/photo_FORMATO_W3SXUOe.png","pontuacao":10.1,"posicao_id":5,"clube_id":356,"entrou_em_campo":true},"105585":{"scout":{"FS":1},"apelido":"Roni","foto":"https://s.sde.globo.com/media/person_role/2024/02/29/photo_FORMATO_jbubVwk.png","pontuacao":0.5,"posicao_id":4,"clube_id":373,"entrou_em_campo":true},"105811":{"scout":{"DS":2,"FC":2,"FD":2,"FF":1,"FS":2,"G":1,"I":2},"apelido":"Wesley","foto":"https://s.sde.globo.com/media/person_role/2024/03/01/photo_FORMATO_X6kjIiZ.png","pontuacao":13.8,"posicao_id":5,"clube_id":285,"entrou_em_campo":true},"105902":{"scout":{"CA":1,"DS":1,"FC":2},"apelido":"Zé Gabriel","foto":"https://s.sde.globo.com/media/person_role/2024/03/04/photo_FORMATO_JGhasXI.png","pontuacao":-0.4,"posicao_id":4,"clube_id":267,"entrou_em_campo":true},"105911":{"scout":{"DS":3,"FC":2,"FD":1,"FS":3},"apelido":"Rômulo","foto":"https://s.sde.globo.com/media/person_role/2024/03/01/photo_FORMATO_lQJeqYA.png","pontuacao":5.7,"posicao_id":4,"clube_id":285,"entrou_em_campo":true},"106147":{"scout":{"V":1},"apelido":"Thiago Carpini","foto":"https://s.sde.globo.com/media/person_role/2024/05/14/photo_FORMATO_IgX32oN.png","pontuacao":6.73,"posicao_id":6,"clube_id":287,"entrou_em_campo":true},"106202":{"scout":{},"apelido":"Bruno Gomes","foto":"https://s.sde.globo.com/media/person_role/2024/02/29/photo_FORMATO_sq3mb5j.png","pontuacao":0,"posicao_id":4,"clube_id":285,"entrou_em_campo":true},"106323":{"scout":{"FS":1},"apelido":"Caio Alexandre","foto":"https://s.sde.globo.com/media/person_role/2024/02/15/photo_FORMATO_jiBs4Bk.png","pontuacao":0.5,"posicao_id":4,"clube_id":265,"entrou_em_campo":true},"106434":{"scout":{"DS":1},"apelido":"Eduardo Santos","foto":"https://s.sde.globo.com/media/person_role/2024/01/03/photo_FORMATO_wPSGjby.png","pontuacao":1.2,"posicao_id":3,"clube_id":280,"entrou_em_campo":true},"106593":{"scout":{"SG":1},"apelido":"Villalba","foto":"https://s.sde.globo.com/media/person_role/2024/03/12/photo_FORMATO_mqCHNug.png","pontuacao":5,"posicao_id":3,"clube_id":283,"entrou_em_campo":true},"106822":{"scout":{},"apelido":"Rodrigo Nestor","foto":"https://s.sde.globo.com/media/person_role/2024/03/01/photo_FORMATO_LPbAkh9.png","pontuacao":0,"posicao_id":4,"clube_id":276,"entrou_em_campo":true},"106824":{"scout":{"DS":3,"FC":1,"FF":1,"FS":2},"apelido":"Welington","foto":"https://s.sde.globo.com/media/person_role/2024/03/01/photo_FORMATO_Z3aNUXx.png","pontuacao":5.1,"posicao_id":2,"clube_id":276,"entrou_em_campo":true},"106931":{"scout":{"DS":1,"FC":5,"FF":1,"FS":1,"I":3},"apelido":"Clayton","foto":"https://s.sde.globo.com/media/person_role/2024/03/12/photo_220x220_tVZpibR.png","pontuacao":0.7,"posicao_id":5,"clube_id":267,"entrou_em_campo":true},"107093":{"scout":{"DS":2},"apelido":"Luciano Juba","foto":"https://s.sde.globo.com/media/person_role/2024/02/29/photo_FORMATO_rR1yZyw.png","pontuacao":2.4,"posicao_id":2,"clube_id":265,"entrou_em_campo":true},"107173":{"scout":{"DS":2,"FD":1,"FF":1,"FS":2},"apelido":"Michel Araújo","foto":"https://s.sde.globo.com/media/person_role/2024/03/01/photo_FORMATO_498ez5E.png","pontuacao":5.4,"posicao_id":4,"clube_id":276,"entrou_em_campo":true},"107179":{"scout":{"DE":4,"GS":1},"apelido":"Matheus Donelli","foto":"https://s.sde.globo.com/media/person_role/2024/02/27/photo_FORMATO_9utJF4u.png","pontuacao":3,"posicao_id":1,"clube_id":264,"entrou_em_campo":true},"107183":{"scout":{"DE":1,"GS":1},"apelido":"Léo Linck","foto":"https://s.sde.globo.com/media/person_role/2024/03/04/photo_FORMATO_bL4Rm1s.png","pontuacao":0,"posicao_id":1,"clube_id":293,"entrou_em_campo":true},"107203":{"scout":{"DS":1,"FT":1},"apelido":"Max","foto":"https://s.sde.globo.com/media/person_role/2024/02/29/photo_FORMATO_tZvTg6Z.png","pontuacao":4.2,"posicao_id":4,"clube_id":1371,"entrou_em_campo":true},"107225":{"scout":{"I":2},"apelido":"Gustavo Garcia","foto":"https://s.sde.globo.com/media/person_role/2024/02/27/photo_FORMATO_jWfyxOy.png","pontuacao":-0.2,"posicao_id":2,"clube_id":275,"entrou_em_campo":true},"107236":{"scout":{},"apelido":"Vanderlan","foto":"https://s.sde.globo.com/media/person_role/2024/02/27/photo_FORMATO_JhaBedf.png","pontuacao":0,"posicao_id":2,"clube_id":275,"entrou_em_campo":true},"107238":{"scout":{"DS":1,"FS":1},"apelido":"Marcelinho","foto":"https://s.sde.globo.com/media/person_role/2024/04/26/photo_FORMATO_1GgfZEe.png","pontuacao":1.7,"posicao_id":5,"clube_id":286,"entrou_em_campo":true},"107256":{"scout":{},"apelido":"Zé Vitor","foto":"https://s.sde.globo.com/media/person_role/2024/04/13/photo_220x220_dAbIrS8.png","pontuacao":0,"posicao_id":4,"clube_id":293,"entrou_em_campo":true},"107908":{"scout":{"DS":1,"FC":1,"FS":2},"apelido":"Hugo","foto":"https://s.sde.globo.com/media/person_role/2024/02/27/photo_FORMATO_h4IhTE1.png","pontuacao":1.9,"posicao_id":2,"clube_id":264,"entrou_em_campo":true},"108133":{"scout":{"DS":1,"FC":1,"FF":1,"FS":1},"apelido":"Isidro Pitta","foto":"https://s.sde.globo.com/media/person_role/2024/02/29/photo_FORMATO_VmtW8Bv.png","pontuacao":2.2,"posicao_id":5,"clube_id":1371,"entrou_em_campo":true},"109282":{"scout":{"FS":1},"apelido":"Luiz Henrique","foto":"https://s.sde.globo.com/media/person_role/2024/04/20/photo_FORMATO_f3wPomL.png","pontuacao":0.5,"posicao_id":5,"clube_id":263,"entrou_em_campo":true},"109461":{"scout":{"CA":1,"FC":2,"FF":1,"FS":1},"apelido":"Calebe","foto":"https://s.sde.globo.com/media/person_role/2024/02/28/photo_FORMATO_zjAtk2u.png","pontuacao":-0.3,"posicao_id":4,"clube_id":356,"entrou_em_campo":true},"109573":{"scout":{"DS":1,"FC":1,"FS":1},"apelido":"Martinelli","foto":"https://s.sde.globo.com/media/person_role/2024/04/09/photo_FORMATO_DxKpmdn.png","pontuacao":1.4,"posicao_id":4,"clube_id":266,"entrou_em_campo":true},"110506":{"scout":{"V":1},"apelido":"Abel Ferreira","foto":"https://s.sde.globo.com/media/person_role/2021/04/27/574e87d52be9d06fd03fa69fefb60255_FORMATO.png","pontuacao":6.62,"posicao_id":6,"clube_id":275,"entrou_em_campo":true},"110667":{"scout":{"FC":1},"apelido":"Machuca","foto":"https://s.sde.globo.com/media/person_role/2024/02/28/photo_FORMATO_aKgahZX.png","pontuacao":-0.3,"posicao_id":5,"clube_id":356,"entrou_em_campo":true},"110668":{"scout":{"CA":1,"FC":1,"FS":1},"apelido":"Esquivel","foto":"https://s.sde.globo.com/media/person_role/2023/05/31/photo_FORMATO_DlnAHYU.png","pontuacao":-0.8,"posicao_id":2,"clube_id":293,"entrou_em_campo":true},"110759":{"scout":{"DS":1,"FD":1,"FS":2},"apelido":"John Kennedy","foto":"https://s.sde.globo.com/media/person_role/2024/04/09/photo_FORMATO_XO4700O.png","pontuacao":3.4,"posicao_id":5,"clube_id":266,"entrou_em_campo":true},"110760":{"scout":{},"apelido":"Biel","foto":"https://s.sde.globo.com/media/person_role/2024/02/29/photo_FORMATO_549ojOA.png","pontuacao":0,"posicao_id":5,"clube_id":265,"entrou_em_campo":true},"111005":{"scout":{"DS":2,"FC":1,"FS":1},"apelido":"Léo Naldi","foto":"https://s.sde.globo.com/media/person_role/2024/04/12/photo_FORMATO_mVG5FsO.png","pontuacao":2.6,"posicao_id":4,"clube_id":287,"entrou_em_campo":true},"111309":{"scout":{"DS":2,"FS":2},"apelido":"Gustavo Martins","foto":"https://s.sde.globo.com/media/person_role/2024/03/11/photo_FORMATO_0UAzL2e.png","pontuacao":3.4,"posicao_id":3,"clube_id":284,"entrou_em_campo":true},"111407":{"scout":{"CA":1,"FC":1},"apelido":"Luis Mandaca","foto":"https://s.sde.globo.com/media/person_role/2024/03/11/photo_FORMATO_ZNLvDib.png","pontuacao":-1.3,"posicao_id":4,"clube_id":286,"entrou_em_campo":true},"111578":{"scout":{},"apelido":"António Oliveira","foto":"https://s.sde.globo.com/media/person_role/2021/04/27/21a131dcff78d521da3297e98526ce48_FORMATO.png","pontuacao":2.81,"posicao_id":6,"clube_id":264,"entrou_em_campo":true},"111682":{"scout":{"FC":1,"FF":1},"apelido":"Adson","foto":"https://s.sde.globo.com/media/person_role/2024/03/04/photo_FORMATO_FdRiLgH.png","pontuacao":0.5,"posicao_id":4,"clube_id":267,"entrou_em_campo":true},"111760":{"scout":{"FS":1},"apelido":"Fabinho","foto":"https://s.sde.globo.com/media/person_role/2024/02/27/photo_FORMATO_jLmJElM.png","pontuacao":0.5,"posicao_id":4,"clube_id":275,"entrou_em_campo":true},"111945":{"scout":{"A":1,"FC":1},"apelido":"Diego Hernández","foto":"https://s.sde.globo.com/media/person_role/2024/04/20/photo_FORMATO_A2or1Su.png","pontuacao":4.7,"posicao_id":4,"clube_id":263,"entrou_em_campo":true},"112869":{"scout":{"DS":4,"FC":1},"apelido":"Aníbal Moreno","foto":"https://s.sde.globo.com/media/person_role/2024/02/27/photo_FORMATO_exCTW9r.png","pontuacao":4.5,"posicao_id":4,"clube_id":275,"entrou_em_campo":true},"112886":{"scout":{"CA":1,"DS":3,"FC":3,"FS":2,"G":1},"apelido":"Lucas Barbosa","foto":"https://s.sde.globo.com/media/person_role/2024/03/11/photo_FORMATO_v69l3WS.png","pontuacao":10.7,"posicao_id":5,"clube_id":286,"entrou_em_campo":true},"112906":{"scout":{"DS":1,"FD":1,"FS":3},"apelido":"Sforza","foto":"https://s.sde.globo.com/media/person_role/2024/02/19/photo_FORMATO.png","pontuacao":3.9,"posicao_id":4,"clube_id":267,"entrou_em_campo":true},"113103":{"scout":{"FF":1},"apelido":"Flaco López","foto":"https://s.sde.globo.com/media/person_role/2024/02/27/photo_FORMATO_leI4Pi1.png","pontuacao":0.8,"posicao_id":5,"clube_id":275,"entrou_em_campo":true},"113157":{"scout":{"FC":1,"FS":1},"apelido":"Nathan Mendes","foto":"https://s.sde.globo.com/media/person_role/2024/02/27/photo_FORMATO_avgtjrS.png","pontuacao":0.2,"posicao_id":2,"clube_id":280,"entrou_em_campo":true},"113158":{"scout":{"FF":1},"apelido":"Marquinhos","foto":"https://s.sde.globo.com/media/person_role/2024/04/09/photo_FORMATO_aBFrEHr.png","pontuacao":0.8,"posicao_id":5,"clube_id":266,"entrou_em_campo":true},"113311":{"scout":{"FC":1},"apelido":"Baltasar Barcia","foto":"https://s.sde.globo.com/media/person_role/2024/02/28/photo_FORMATO_vAZLl3s.png","pontuacao":-0.3,"posicao_id":4,"clube_id":288,"entrou_em_campo":true},"113687":{"scout":{"FD":1,"FF":1},"apelido":"Du Queiroz","foto":"https://s.sde.globo.com/media/person_role/2024/03/11/photo_FORMATO_XOn9XLw.png","pontuacao":2,"posicao_id":4,"clube_id":284,"entrou_em_campo":true},"114334":{"scout":{},"apelido":"Gamarra","foto":"https://s.sde.globo.com/media/person_role/2024/01/10/photo_FORMATO_IjL8XS2.png","pontuacao":0,"posicao_id":3,"clube_id":293,"entrou_em_campo":true},"114790":{"scout":{"FF":1},"apelido":"Cleiton","foto":"https://s.sde.globo.com/media/person_role/2024/02/26/photo_FORMATO_TNiLoQL.png","pontuacao":0.8,"posicao_id":3,"clube_id":262,"entrou_em_campo":true},"115239":{"scout":{"DS":1,"FS":2},"apelido":"Wesley","foto":"https://s.sde.globo.com/media/person_role/2024/02/26/photo_FORMATO_zY4BtV3.png","pontuacao":2.2,"posicao_id":2,"clube_id":262,"entrou_em_campo":true},"115246":{"scout":{"DS":1,"FC":1},"apelido":"Naves","foto":"https://s.sde.globo.com/media/person_role/2024/02/27/photo_FORMATO_SDs96Yd.png","pontuacao":0.9,"posicao_id":3,"clube_id":275,"entrou_em_campo":true},"115248":{"scout":{},"apelido":"Jhon Jhon","foto":"https://s.sde.globo.com/media/person_role/2024/02/27/photo_FORMATO_VLklPue.png","pontuacao":0,"posicao_id":4,"clube_id":275,"entrou_em_campo":true},"115268":{"scout":{"CA":1,"DS":1,"FC":1},"apelido":"Rômulo","foto":"https://s.sde.globo.com/media/person_role/2024/04/13/photo_FORMATO_MSj6UGK.png","pontuacao":-0.1,"posicao_id":3,"clube_id":282,"entrou_em_campo":true},"115914":{"scout":{"DS":1},"apelido":"Evertton Araújo","foto":"https://s.sde.globo.com/media/person_role/2023/04/11/photo_FORMATO_TQMbzmd.png","pontuacao":1.2,"posicao_id":4,"clube_id":262,"entrou_em_campo":true},"115986":{"scout":{"DS":2,"FD":1},"apelido":"Denilson","foto":"https://s.sde.globo.com/media/person_role/2024/02/29/photo_FORMATO_dCrOJqx.png","pontuacao":3.6,"posicao_id":4,"clube_id":1371,"entrou_em_campo":true},"116065":{"scout":{"DS":2,"FC":2,"FF":3,"FS":3},"apelido":"Cuiabano","foto":"https://s.sde.globo.com/media/person_role/2024/06/11/photo_FORMATO_EU50mMf.png","pontuacao":5.7,"posicao_id":2,"clube_id":263,"entrou_em_campo":true},"116447":{"scout":{"DS":2},"apelido":"Hércules","foto":"https://s.sde.globo.com/media/person_role/2024/02/28/photo_FORMATO_THe8tWf.png","pontuacao":2.4,"posicao_id":4,"clube_id":356,"entrou_em_campo":true},"116994":{"scout":{"FC":1,"FF":1},"apelido":"Popó","foto":"https://s.sde.globo.com/media/person_role/2024/03/11/photo_FORMATO_EiH3NWS.png","pontuacao":0.5,"posicao_id":5,"clube_id":286,"entrou_em_campo":true},"117314":{"scout":{"DS":1},"apelido":"Thiago Borbas","foto":"https://s.sde.globo.com/media/person_role/2024/01/03/photo_FORMATO_B328S5W.png","pontuacao":1.2,"posicao_id":5,"clube_id":280,"entrou_em_campo":true},"117330":{"scout":{"DS":3,"FC":2,"FF":1,"SG":1},"apelido":"Robert Renan","foto":"https://s.sde.globo.com/media/person_role/2024/03/01/photo_FORMATO_cScwdGd.png","pontuacao":8.8,"posicao_id":3,"clube_id":285,"entrou_em_campo":true},"117579":{"scout":{"DS":1,"FC":2,"FF":1},"apelido":"Galoppo","foto":"https://s.sde.globo.com/media/person_role/2024/03/01/photo_FORMATO_EntLJJn.png","pontuacao":1.4,"posicao_id":4,"clube_id":276,"entrou_em_campo":true},"117622":{"scout":{"DS":1},"apelido":"Alejo Cruz","foto":"https://s.sde.globo.com/media/person_role/2024/02/28/photo_FORMATO_4JP0Dfv.png","pontuacao":1.2,"posicao_id":5,"clube_id":373,"entrou_em_campo":true},"117632":{"scout":{"CA":1,"DS":1,"FC":1,"FD":1,"FF":1,"FS":4,"I":1},"apelido":"Garro","foto":"https://s.sde.globo.com/media/person_role/2024/02/27/photo_FORMATO_5Gp0vVv.png","pontuacao":3.8,"posicao_id":4,"clube_id":264,"entrou_em_campo":true},"117711":{"scout":{},"apelido":"Pedro Caixinha","foto":"https://s.sde.globo.com/media/person_role/2023/03/06/photo_FORMATO_LvzP4JH.png","pontuacao":3.7,"posicao_id":6,"clube_id":280,"entrou_em_campo":true},"117842":{"scout":{"FC":1},"apelido":"Vitinho","foto":"https://s.sde.globo.com/media/person_role/2024/03/02/photo_FORMATO_bhMj4uh.png","pontuacao":-0.3,"posicao_id":4,"clube_id":283,"entrou_em_campo":true},"117909":{"scout":{"DS":3,"FS":1},"apelido":"Wesley","foto":"https://s.sde.globo.com/media/person_role/2024/02/27/photo_FORMATO_KAHpgBA.png","pontuacao":4.1,"posicao_id":5,"clube_id":264,"entrou_em_campo":true},"117910":{"scout":{"DS":3,"FC":2,"FS":1},"apelido":"Breno Bidon","foto":"https://s.sde.globo.com/media/person_role/2022/07/02/7c27a7fcaaaccdedd144a0e9af0c0e2d_FORMATO.png","pontuacao":3.5,"posicao_id":4,"clube_id":264,"entrou_em_campo":true},"118745":{"scout":{"G":1},"apelido":"Eliel","foto":"https://s.sde.globo.com/media/person_role/2024/02/29/photo_FORMATO_t0Fw29t.png","pontuacao":8,"posicao_id":5,"clube_id":1371,"entrou_em_campo":true},"118752":{"scout":{"DS":1,"FS":2},"apelido":"Mateus Carvalho","foto":"https://s.sde.globo.com/media/person_role/2024/03/04/photo_FORMATO_JfIekB6.png","pontuacao":2.2,"posicao_id":4,"clube_id":267,"entrou_em_campo":true},"122321":{"scout":{"FC":2,"FD":1,"FS":1,"I":1},"apelido":"Lorran","foto":"https://s.sde.globo.com/media/person_role/2023/03/14/photo_FORMATO_PqkKiZh.png","pontuacao":1,"posicao_id":4,"clube_id":262,"entrou_em_campo":true},"122393":{"scout":{},"apelido":"Talisson","foto":"https://s.sde.globo.com/media/person_role/2024/01/03/photo_FORMATO_HTUJbDI.png","pontuacao":0,"posicao_id":5,"clube_id":280,"entrou_em_campo":true},"122394":{"scout":{"DS":1},"apelido":"Gustavinho","foto":"https://s.sde.globo.com/media/person_role/2024/01/03/photo_FORMATO_ayQ4fZH.png","pontuacao":1.2,"posicao_id":4,"clube_id":280,"entrou_em_campo":true},"122413":{"scout":{"FC":1},"apelido":"Pablo Baianinho","foto":"https://s.sde.globo.com/media/person_role/2024/04/12/photo_FORMATO_58gJ7zZ.png","pontuacao":-0.3,"posicao_id":4,"clube_id":287,"entrou_em_campo":true},"122486":{"scout":{},"apelido":"Rayan","foto":"https://s.sde.globo.com/media/person_role/2024/03/04/photo_FORMATO_DAjK7yT.png","pontuacao":0,"posicao_id":5,"clube_id":267,"entrou_em_campo":true},"122660":{"scout":{},"apelido":"Japa","foto":"https://s.sde.globo.com/media/person_role/2024/03/01/photo_FORMATO_7IIL65y.png","pontuacao":0,"posicao_id":4,"clube_id":283,"entrou_em_campo":true},"122887":{"scout":{"DS":2,"FC":1},"apelido":"Emiliano Rodríguez","foto":"https://s.sde.globo.com/media/person_role/2024/02/29/photo_FORMATO_1aZ2q89.png","pontuacao":2.1,"posicao_id":5,"clube_id":373,"entrou_em_campo":true},"123359":{"scout":{"DS":1,"FC":3,"FF":1,"FS":2,"I":1},"apelido":"Cadu","foto":"https://s.sde.globo.com/media/person_role/2023/04/13/photo_FORMATO_FDCeBal.png","pontuacao":2,"posicao_id":5,"clube_id":282,"entrou_em_campo":true},"123360":{"scout":{"FF":1,"FS":2},"apelido":"Cauly","foto":"https://s.sde.globo.com/media/person_role/2024/02/29/photo_FORMATO_31M3s89.png","pontuacao":1.8,"posicao_id":4,"clube_id":265,"entrou_em_campo":true},"123873":{"scout":{"FD":1,"G":1},"apelido":"Palacios","foto":"https://s.sde.globo.com/media/person_role/2024/03/07/photo_220x220_b3oriPT.png","pontuacao":9.2,"posicao_id":5,"clube_id":282,"entrou_em_campo":true},"123960":{"scout":{"FS":1},"apelido":"Fábio","foto":"https://s.sde.globo.com/media/person_role/2024/04/12/photo_FORMATO_ipoYISJ.png","pontuacao":0.5,"posicao_id":5,"clube_id":287,"entrou_em_campo":true},"124239":{"scout":{"FC":1,"FF":1},"apelido":"Henry Mosquera","foto":"https://s.sde.globo.com/media/person_role/2024/01/03/photo_FORMATO_id8Dwn8.png","pontuacao":0.5,"posicao_id":5,"clube_id":280,"entrou_em_campo":true},"124247":{"scout":{"FF":1},"apelido":"Isaac","foto":"https://s.sde.globo.com/media/person_role/2023/04/22/photo_FORMATO_3csZZPr.png","pontuacao":0.8,"posicao_id":5,"clube_id":282,"entrou_em_campo":true},"124757":{"scout":{"FF":1,"FS":1},"apelido":"Nathan Fernandes","foto":"https://s.sde.globo.com/media/person_role/2024/03/11/photo_FORMATO_nzWNsYv.png","pontuacao":1.3,"posicao_id":5,"clube_id":284,"entrou_em_campo":true},"124821":{"scout":{"FC":1},"apelido":"Kauã Elias","foto":"https://s.sde.globo.com/media/person_role/2024/04/09/photo_FORMATO_UGP7Pol.png","pontuacao":-0.3,"posicao_id":5,"clube_id":266,"entrou_em_campo":true},"125050":{"scout":{"CA":1,"FF":1,"FS":1,"I":1},"apelido":"Robert","foto":"https://s.sde.globo.com/media/person_role/2024/03/02/photo_FORMATO_0Vl4WfI.png","pontuacao":0.2,"posicao_id":5,"clube_id":283,"entrou_em_campo":true},"125469":{"scout":{"DS":2,"FD":1,"FF":2},"apelido":"Alisson","foto":"https://s.sde.globo.com/media/person_role/2024/03/12/photo_FORMATO_THGcoZm.png","pontuacao":5.2,"posicao_id":4,"clube_id":282,"entrou_em_campo":true},"125471":{"scout":{"CA":1,"DS":1,"FC":1,"FD":1,"FS":2,"I":1},"apelido":"Serginho","foto":"https://s.sde.globo.com/media/person_role/2024/03/04/photo_FORMATO_ytTWQ9L.png","pontuacao":2,"posicao_id":5,"clube_id":267,"entrou_em_campo":true},"126117":{"scout":{"DS":1,"I":2},"apelido":"Gustavo Nunes","foto":"https://s.sde.globo.com/media/person_role/2024/03/13/photo_FORMATO.png","pontuacao":1,"posicao_id":5,"clube_id":284,"entrou_em_campo":true},"126900":{"scout":{"DS":1,"FC":1,"FD":1,"FF":2,"FS":1},"apelido":"Igor Coronado","foto":"https://s.sde.globo.com/media/person_role/2024/02/27/photo_FORMATO_Bzw6tC2.png","pontuacao":4.2,"posicao_id":4,"clube_id":264,"entrou_em_campo":true},"126977":{"scout":{"V":1},"apelido":"Fernando Seabra","foto":"https://s.sde.globo.com/media/person_role/2024/04/09/photo_220x220_GrLAgQt.png","pontuacao":7.55,"posicao_id":6,"clube_id":283,"entrou_em_campo":true},"127273":{"scout":{},"apelido":"Artur Jorge","foto":"https://s.sde.globo.com/media/person_role/2024/04/05/photo_220x220_4pgYWQ9.png","pontuacao":3.92,"posicao_id":6,"clube_id":263,"entrou_em_campo":true},"128668":{"scout":{"CA":1,"FD":1,"I":1},"apelido":"William Gomes","foto":"https://s.sde.globo.com/media/person_role/2024/03/01/photo_FORMATO_R4UlTHA.png","pontuacao":0.1,"posicao_id":5,"clube_id":276,"entrou_em_campo":true},"128915":{"scout":{"DS":2,"FC":2,"FD":2,"FF":2},"apelido":"Estêvão","foto":"https://s.sde.globo.com/media/person_role/2024/02/27/photo_FORMATO_ndyx6H0.png","pontuacao":5.8,"posicao_id":5,"clube_id":275,"entrou_em_campo":true},"129227":{"scout":{"DS":1},"apelido":"Zuleta","foto":"https://s.sde.globo.com/media/person_role/2024/02/28/photo_FORMATO_IBrilAp.png","pontuacao":1.2,"posicao_id":4,"clube_id":373,"entrou_em_campo":true},"129666":{"scout":{},"apelido":"JP","foto":"https://s.sde.globo.com/media/person_role/2024/03/04/photo_FORMATO_bBaUSEp.png","pontuacao":0,"posicao_id":4,"clube_id":267,"entrou_em_campo":true},"129766":{"scout":{"FS":1},"apelido":"Max","foto":"https://s.sde.globo.com/media/person_role/2024/03/16/photo_FORMATO_czuX078.png","pontuacao":0.5,"posicao_id":5,"clube_id":373,"entrou_em_campo":true},"130020":{"scout":{"FC":1},"apelido":"Luiz Gustavo","foto":"","pontuacao":-0.3,"posicao_id":3,"clube_id":373,"entrou_em_campo":true},"130414":{"scout":{"FS":1},"apelido":"Robert Santos","foto":"https://s.sde.globo.com/media/person_role/2024/03/27/photo_FORMATO_nXUDlTZ.png","pontuacao":0.5,"posicao_id":4,"clube_id":282,"entrou_em_campo":true},"131512":{"scout":{},"apelido":"Yarlen","foto":"https://s.sde.globo.com/media/person_role/2024/04/20/photo_FORMATO_yss1MD0.png","pontuacao":0,"posicao_id":5,"clube_id":263,"entrou_em_campo":true},"132733":{"scout":{"DS":2,"FS":3},"apelido":"Fabiano","foto":null,"pontuacao":3.9,"posicao_id":5,"clube_id":263,"entrou_em_campo":true},"132984":{"scout":{},"apelido":"Álvaro Pacheco","foto":"https://s.sde.globo.com/media/person_role/2024/05/21/photo_FORMATO_xCm41NL.png","pontuacao":1.23,"posicao_id":6,"clube_id":267,"entrou_em_campo":true},"133566":{"scout":{"FC":1},"apelido":"Lucca Drummond","foto":"","pontuacao":-0.3,"posicao_id":5,"clube_id":285,"entrou_em_campo":true},"37656":{"scout":{"DE":4,"GS":2},"apelido":"Fábio","foto":"https://s.sde.globo.com/media/person_role/2024/04/09/photo_FORMATO_kG7j2Bl.png","pontuacao":2,"posicao_id":1,"clube_id":266,"entrou_em_campo":true},"38394":{"scout":{"DS":2,"FC":1,"FF":2,"FS":1},"apelido":"Thiago Heleno","foto":"https://s.sde.globo.com/media/person_role/2024/03/05/photo_FORMATO_RN1xUpJ.png","pontuacao":4.2,"posicao_id":3,"clube_id":293,"entrou_em_campo":true},"38398":{"scout":{"DS":1,"FC":1,"FS":1},"apelido":"Renato Augusto","foto":"https://s.sde.globo.com/media/person_role/2024/04/09/photo_FORMATO_5yW5MSp.png","pontuacao":1.4,"posicao_id":4,"clube_id":266,"entrou_em_campo":true},"38913":{"scout":{"FC":1,"FD":1,"FS":3},"apelido":"Nenê","foto":"https://s.sde.globo.com/media/person_role/2024/03/11/photo_FORMATO_h0cWmA3.png","pontuacao":2.4,"posicao_id":4,"clube_id":286,"entrou_em_campo":true},"38959":{"scout":{},"apelido":"Vagner Love","foto":"https://s.sde.globo.com/media/person_role/2024/02/28/photo_FORMATO_BmOmgCS.png","pontuacao":0,"posicao_id":5,"clube_id":373,"entrou_em_campo":true},"41929":{"scout":{},"apelido":"Renato Gaúcho","foto":"https://s.sde.globo.com/media/person_role/2021/07/12/a1f0a8f108ede4bf4ca2033148bcb547_FORMATO.png","pontuacao":1.45,"posicao_id":6,"clube_id":284,"entrou_em_campo":true},"42222":{"scout":{"DS":2,"FC":3,"FF":1,"FS":2,"PC":1},"apelido":"Osvaldo","foto":"https://s.sde.globo.com/media/person_role/2024/04/12/photo_FORMATO_ehAae2c.png","pontuacao":2.3,"posicao_id":5,"clube_id":287,"entrou_em_campo":true},"42411":{"scout":{},"apelido":"Cuca","foto":"https://s.sde.globo.com/media/person_role/2021/04/27/0ea32497ac7f6b6b22649eecca984fec_FORMATO.png","pontuacao":3.25,"posicao_id":6,"clube_id":293,"entrou_em_campo":true},"45125":{"scout":{"V":1},"apelido":"Tite","foto":"https://s.sde.globo.com/media/person_role/2023/10/09/photo_FORMATO_KL4MJhP.png","pontuacao":5.52,"posicao_id":6,"clube_id":262,"entrou_em_campo":true},"50347":{"scout":{"FF":1},"apelido":"Alan Kardec","foto":"https://s.sde.globo.com/media/person_role/2023/03/31/photo_FORMATO_vFJpxe5.png","pontuacao":0.8,"posicao_id":5,"clube_id":282,"entrou_em_campo":true},"50353":{"scout":{"DS":4,"FC":1,"SG":1},"apelido":"Titi","foto":"https://s.sde.globo.com/media/person_role/2024/02/28/photo_FORMATO_xJrxKei.png","pontuacao":9.5,"posicao_id":3,"clube_id":356,"entrou_em_campo":true},"51413":{"scout":{"DE":4,"SG":1},"apelido":"Walter","foto":"https://s.sde.globo.com/media/person_role/2024/02/29/photo_FORMATO_1t3HUJH.png","pontuacao":9,"posicao_id":1,"clube_id":1371,"entrou_em_campo":true},"51772":{"scout":{"FC":1,"FD":1,"FS":1},"apelido":"Everton Ribeiro","foto":"https://s.sde.globo.com/media/person_role/2024/02/15/photo_FORMATO_NvwmZSj.png","pontuacao":1.4,"posicao_id":4,"clube_id":265,"entrou_em_campo":true},"52271":{"scout":{"FC":1},"apelido":"Fernando","foto":"https://s.sde.globo.com/media/person_role/2024/02/29/photo_FORMATO_OiqMDlL.png","pontuacao":-0.3,"posicao_id":4,"clube_id":285,"entrou_em_campo":true},"52827":{"scout":{"DS":1,"FF":1,"G":1},"apelido":"David Luiz","foto":"https://s.sde.globo.com/media/person_role/2024/02/26/photo_FORMATO_5AohPGw.png","pontuacao":10,"posicao_id":3,"clube_id":262,"entrou_em_campo":true},"61188":{"scout":{"FC":1,"FD":1,"FF":1,"I":1},"apelido":"Gilberto","foto":"https://s.sde.globo.com/media/person_role/2024/03/11/photo_FORMATO_pf8CAXv.png","pontuacao":1.6,"posicao_id":5,"clube_id":286,"entrou_em_campo":true},"61228":{"scout":{"DE":3,"SG":1},"apelido":"Fabrício","foto":"https://s.sde.globo.com/media/person_role/2024/06/11/photo_FORMATO_zdmyueQ.png","pontuacao":8,"posicao_id":1,"clube_id":285,"entrou_em_campo":true},"62020":{"scout":{"FF":1},"apelido":"Douglas Costa","foto":"https://s.sde.globo.com/media/person_role/2024/04/09/photo_FORMATO_rhXFmGa.png","pontuacao":0.8,"posicao_id":5,"clube_id":266,"entrou_em_campo":true},"63289":{"scout":{"CA":1,"FC":1},"apelido":"Edenílson","foto":"https://s.sde.globo.com/media/person_role/2024/04/19/photo_FORMATO_TU1lzBm.png","pontuacao":-1.3,"posicao_id":4,"clube_id":284,"entrou_em_campo":true},"68708":{"scout":{"FC":1,"FS":1},"apelido":"Eduardo","foto":"https://s.sde.globo.com/media/person_role/2024/04/20/photo_FORMATO_oIeJUEt.png","pontuacao":0.2,"posicao_id":4,"clube_id":263,"entrou_em_campo":true},"68954":{"scout":{"FC":2,"FF":1,"FS":1},"apelido":"Marquinhos Gabriel","foto":"https://s.sde.globo.com/media/person_role/2024/01/16/photo_FORMATO_cYCP9RY.png","pontuacao":0.7,"posicao_id":4,"clube_id":288,"entrou_em_campo":true},"68991":{"scout":{"FC":3},"apelido":"Lucas Sasha","foto":"https://s.sde.globo.com/media/person_role/2024/02/28/photo_FORMATO_YNCB9SE.png","pontuacao":-0.9,"posicao_id":4,"clube_id":356,"entrou_em_campo":true},"69138":{"scout":{"CA":1,"FC":1},"apelido":"Pablo","foto":"https://s.sde.globo.com/media/person_role/2024/03/05/photo_FORMATO_9SQlsjr.png","pontuacao":-1.3,"posicao_id":5,"clube_id":293,"entrou_em_campo":true},"69325":{"scout":{"CA":1,"FC":1},"apelido":"Aránguiz","foto":"https://s.sde.globo.com/media/person_role/2024/02/29/photo_FORMATO_NLgDxgG.png","pontuacao":-1.3,"posicao_id":4,"clube_id":285,"entrou_em_campo":true},"69686":{"scout":{"FC":2},"apelido":"João Pedro Galvão","foto":"https://s.sde.globo.com/media/person_role/2024/03/11/photo_FORMATO_Trda9pv.png","pontuacao":-0.6,"posicao_id":5,"clube_id":284,"entrou_em_campo":true},"69705":{"scout":{"FF":2,"FS":6},"apelido":"Nikão","foto":"https://s.sde.globo.com/media/person_role/2024/04/22/photo_FORMATO_k9LXARi.png","pontuacao":4.6,"posicao_id":4,"clube_id":293,"entrou_em_campo":true},"70164":{"scout":{"FF":1},"apelido":"Lucas Moura","foto":"https://s.sde.globo.com/media/person_role/2024/03/01/photo_FORMATO_3fFiGsF.png","pontuacao":0.8,"posicao_id":4,"clube_id":276,"entrou_em_campo":true},"70332":{"scout":{"CA":1,"DE":3,"GS":1},"apelido":"Marchesín","foto":"https://s.sde.globo.com/media/person_role/2024/03/11/photo_FORMATO_PpXRpkU.png","pontuacao":1,"posicao_id":1,"clube_id":284,"entrou_em_campo":true},"70360":{"scout":{"A":1,"FF":1,"FS":1},"apelido":"Eduardo Sasha","foto":"https://s.sde.globo.com/media/person_role/2024/01/03/photo_FORMATO_vmWK3aR.png","pontuacao":6.3,"posicao_id":5,"clube_id":280,"entrou_em_campo":true},"70449":{"scout":{"DE":2,"SG":1},"apelido":"Gabriel","foto":"https://s.sde.globo.com/media/person_role/2024/03/11/photo_FORMATO_8qXDLkA.png","pontuacao":7,"posicao_id":1,"clube_id":286,"entrou_em_campo":true},"70666":{"scout":{"FC":2,"FF":1,"SG":1},"apelido":"Marllon","foto":"https://s.sde.globo.com/media/person_role/2024/02/29/photo_FORMATO_r4ei6c2.png","pontuacao":5.2,"posicao_id":3,"clube_id":1371,"entrou_em_campo":true},"70916":{"scout":{"CA":1,"DS":2,"FC":1,"FS":1},"apelido":"Diogo Barbosa","foto":"https://s.sde.globo.com/media/person_role/2024/04/09/photo_FORMATO_u4ftkcX.png","pontuacao":1.6,"posicao_id":2,"clube_id":266,"entrou_em_campo":true},"70944":{"scout":{"DS":4,"FC":3,"FF":1},"apelido":"Bruno Henrique","foto":"https://s.sde.globo.com/media/person_role/2024/02/29/photo_FORMATO_CD57Ckc.png","pontuacao":4.7,"posicao_id":4,"clube_id":285,"entrou_em_campo":true},"70958":{"scout":{"DS":1,"G":1},"apelido":"Jean Carlos","foto":"https://s.sde.globo.com/media/person_role/2024/03/11/photo_FORMATO_4HRxczb.png","pontuacao":9.2,"posicao_id":4,"clube_id":286,"entrou_em_campo":true},"71038":{"scout":{"CA":1,"DS":1,"FC":4},"apelido":"Pedro Henrique","foto":"https://s.sde.globo.com/media/person_role/2024/02/28/photo_FORMATO_Es6RFmf.png","pontuacao":-1,"posicao_id":3,"clube_id":373,"entrou_em_campo":true},"71227":{"scout":{"DS":3},"apelido":"Maicon","foto":"https://s.sde.globo.com/media/person_role/2024/03/04/photo_FORMATO_zkGlvKC.png","pontuacao":3.6,"posicao_id":3,"clube_id":267,"entrou_em_campo":true},"71536":{"scout":{"FF":1},"apelido":"Luiz Gustavo","foto":"https://s.sde.globo.com/media/person_role/2024/03/01/photo_FORMATO_nt2TzmF.png","pontuacao":0.8,"posicao_id":4,"clube_id":276,"entrou_em_campo":true},"71631":{"scout":{"A":1,"DE":2,"GS":1},"apelido":"Weverton","foto":"https://s.sde.globo.com/media/person_role/2024/02/27/photo_FORMATO_pwFJ9Uo.png","pontuacao":6,"posicao_id":1,"clube_id":275,"entrou_em_campo":true},"71680":{"scout":{"A":1,"DS":3},"apelido":"Raúl Cáceres","foto":"https://s.sde.globo.com/media/person_role/2024/04/12/photo_FORMATO_lPclyZL.png","pontuacao":8.6,"posicao_id":2,"clube_id":287,"entrou_em_campo":true},"71898":{"scout":{"FS":3},"apelido":"Gabriel Pires","foto":"https://s.sde.globo.com/media/person_role/2024/04/09/photo_FORMATO_084ZZNa.png","pontuacao":1.5,"posicao_id":4,"clube_id":266,"entrou_em_campo":true},"72294":{"scout":{"DE":1,"GS":4},"apelido":"Everson","foto":"https://s.sde.globo.com/media/person_role/2023/03/31/photo_FORMATO_r7CD0SX.png","pontuacao":-3,"posicao_id":1,"clube_id":282,"entrou_em_campo":true},"72391":{"scout":{},"apelido":"Fernando Diniz","foto":"https://s.sde.globo.com/media/person_role/2023/03/01/photo_FORMATO_dcBENR5.png","pontuacao":2.21,"posicao_id":6,"clube_id":266,"entrou_em_campo":true},"72532":{"scout":{"DS":1,"FC":1,"FF":1,"FS":4},"apelido":"Maguinho","foto":"https://s.sde.globo.com/media/person_role/2024/02/29/photo_FORMATO_204au3d.png","pontuacao":3.7,"posicao_id":2,"clube_id":373,"entrou_em_campo":true},"72775":{"scout":{"DS":1,"FC":2,"FD":2,"FS":2},"apelido":"Fernandinho","foto":"https://s.sde.globo.com/media/person_role/2024/03/01/photo_FORMATO_G29hOpk.png","pontuacao":4,"posicao_id":4,"clube_id":293,"entrou_em_campo":true},"72951":{"scout":{"FS":1,"SG":1},"apelido":"Mercado","foto":"https://s.sde.globo.com/media/person_role/2024/02/29/photo_FORMATO_o74D2pK.png","pontuacao":5.5,"posicao_id":3,"clube_id":285,"entrou_em_campo":true},"73620":{"scout":{"FC":1,"SG":1},"apelido":"Bruno Alves","foto":"https://s.sde.globo.com/media/person_role/2024/02/29/photo_FORMATO_k3QDtbn.png","pontuacao":4.7,"posicao_id":3,"clube_id":1371,"entrou_em_campo":true},"78117":{"scout":{"DS":2,"FC":2,"FF":1,"G":1,"I":1},"apelido":"Everaldo","foto":"https://s.sde.globo.com/media/person_role/2024/02/29/photo_FORMATO_ZTjMF4T.png","pontuacao":10.5,"posicao_id":5,"clube_id":265,"entrou_em_campo":true},"78248":{"scout":{"FC":1,"FF":1},"apelido":"Gustavo Henrique","foto":"https://s.sde.globo.com/media/person_role/2024/02/27/photo_FORMATO_eaP6jN7.png","pontuacao":0.5,"posicao_id":3,"clube_id":264,"entrou_em_campo":true},"78450":{"scout":{"V":1},"apelido":"Cláudio Tencati","foto":"https://s.sde.globo.com/media/person_role/2024/03/25/photo_FORMATO_54lwaii.png","pontuacao":4.5,"posicao_id":6,"clube_id":288,"entrou_em_campo":true},"78548":{"scout":{"FC":1},"apelido":"Jean Mota","foto":"https://s.sde.globo.com/media/person_role/2024/04/12/photo_FORMATO_hp4AXuX.png","pontuacao":-0.3,"posicao_id":4,"clube_id":287,"entrou_em_campo":true},"78580":{"scout":{"DS":1,"FC":2,"FF":2,"FS":2},"apelido":"Jonathan Cafu","foto":"https://s.sde.globo.com/media/person_role/2024/02/29/photo_FORMATO_EstVL0K.png","pontuacao":3.2,"posicao_id":5,"clube_id":1371,"entrou_em_campo":true},"78715":{"scout":{"DS":2,"FC":3,"FS":1},"apelido":"Ramiro","foto":"https://s.sde.globo.com/media/person_role/2024/03/02/photo_FORMATO_MK4CCfT.png","pontuacao":2,"posicao_id":4,"clube_id":283,"entrou_em_campo":true},"78850":{"scout":{"CA":1,"DS":1,"FC":1,"I":1},"apelido":"Reinaldo","foto":"https://s.sde.globo.com/media/person_role/2024/03/11/photo_FORMATO_v8J7R5r.png","pontuacao":-0.2,"posicao_id":2,"clube_id":284,"entrou_em_campo":true},"78855":{"scout":{"CA":1,"FC":1,"PC":1},"apelido":"Thiago Santos","foto":"https://s.sde.globo.com/media/person_role/2024/04/09/photo_FORMATO_L3ovhxb.png","pontuacao":-2.3,"posicao_id":3,"clube_id":266,"entrou_em_campo":true},"79437":{"scout":{"V":1},"apelido":"Roger Machado","foto":"https://s.sde.globo.com/media/person_role/2021/04/27/ec1e7e490c3a05088fd967b9e2468216_FORMATO.png","pontuacao":7.5,"posicao_id":6,"clube_id":286,"entrou_em_campo":true},"79631":{"scout":{"FD":1,"FF":2},"apelido":"Cano","foto":"https://s.sde.globo.com/media/person_role/2024/04/09/photo_FORMATO_uSA2481.png","pontuacao":2.8,"posicao_id":5,"clube_id":266,"entrou_em_campo":true},"79701":{"scout":{"DS":1,"FC":1,"FD":1,"FF":1,"FS":1},"apelido":"Lucas Silva","foto":"https://s.sde.globo.com/media/person_role/2024/03/01/photo_FORMATO_KnivRCo.png","pontuacao":3.4,"posicao_id":4,"clube_id":283,"entrou_em_campo":true},"79702":{"scout":{"FS":2},"apelido":"Antônio Carlos","foto":"https://s.sde.globo.com/media/person_role/2024/04/09/photo_FORMATO_Cwpf6R7.png","pontuacao":1,"posicao_id":3,"clube_id":266,"entrou_em_campo":true},"80129":{"scout":{"DS":4,"FC":3,"FD":1,"FS":2},"apelido":"Jadson","foto":"https://s.sde.globo.com/media/person_role/2024/03/11/photo_FORMATO_1INRw87.png","pontuacao":6.1,"posicao_id":4,"clube_id":286,"entrou_em_campo":true},"80196":{"scout":{"FC":1,"FS":2},"apelido":"Yago Pikachu","foto":"https://s.sde.globo.com/media/person_role/2024/02/28/photo_FORMATO_QAL0UhA.png","pontuacao":0.7,"posicao_id":4,"clube_id":356,"entrou_em_campo":true},"80287":{"scout":{"FD":1,"FF":1,"FS":2},"apelido":"Luciano","foto":"https://s.sde.globo.com/media/person_role/2024/03/01/photo_FORMATO_hqCxZF4.png","pontuacao":3,"posicao_id":5,"clube_id":276,"entrou_em_campo":true},"80313":{"scout":{"DS":1,"FC":2,"FS":2,"I":1},"apelido":"Gilberto","foto":"https://s.sde.globo.com/media/person_role/2024/02/29/photo_FORMATO_iy1T2ej.png","pontuacao":1.5,"posicao_id":2,"clube_id":265,"entrou_em_campo":true},"80337":{"scout":{"FD":1,"FS":5,"I":3},"apelido":"Arthur Caíke","foto":"https://s.sde.globo.com/media/person_role/2024/04/12/photo_220x220.png","pontuacao":3.4,"posicao_id":5,"clube_id":288,"entrou_em_campo":true},"81150":{"scout":{"DS":3,"FS":2},"apelido":"Mayke","foto":"https://s.sde.globo.com/media/person_role/2024/02/27/photo_FORMATO_pz3GebS.png","pontuacao":4.6,"posicao_id":2,"clube_id":275,"entrou_em_campo":true},"81551":{"scout":{"SG":1},"apelido":"Hugo Mallo","foto":"https://s.sde.globo.com/media/person_role/2024/02/29/photo_FORMATO_CBzQtxz.png","pontuacao":5,"posicao_id":2,"clube_id":285,"entrou_em_campo":true},"81798":{"scout":{"DS":1},"apelido":"Rossi","foto":"https://s.sde.globo.com/media/person_role/2024/03/04/photo_FORMATO_8UqKNri.png","pontuacao":1.2,"posicao_id":5,"clube_id":267,"entrou_em_campo":true},"81845":{"scout":{"CA":1,"DS":3,"FF":1,"FS":1},"apelido":"Alisson","foto":"https://s.sde.globo.com/media/person_role/2024/03/01/photo_FORMATO_fS2GyF1.png","pontuacao":3.9,"posicao_id":4,"clube_id":276,"entrou_em_campo":true},"81881":{"scout":{"DE":2,"SG":1},"apelido":"João Ricardo","foto":"https://s.sde.globo.com/media/person_role/2024/02/28/photo_FORMATO_yXqoxi8.png","pontuacao":7,"posicao_id":1,"clube_id":356,"entrou_em_campo":true},"81952":{"scout":{"DS":1,"FC":2,"FS":3,"G":2},"apelido":"Willian Oliveira","foto":"https://s.sde.globo.com/media/person_role/2024/04/12/photo_FORMATO_AuUF822.png","pontuacao":18.1,"posicao_id":4,"clube_id":287,"entrou_em_campo":true},"82455":{"scout":{"DS":3,"FC":1},"apelido":"Zé Rafael","foto":"https://s.sde.globo.com/media/person_role/2024/02/27/photo_FORMATO_BAUllGq.png","pontuacao":3.3,"posicao_id":4,"clube_id":275,"entrou_em_campo":true},"82627":{"scout":{"DS":1,"FF":1,"FS":1},"apelido":"Luiz Araújo","foto":"https://s.sde.globo.com/media/person_role/2024/02/26/photo_FORMATO_HkAAcVs.png","pontuacao":2.5,"posicao_id":5,"clube_id":262,"entrou_em_campo":true},"82628":{"scout":{"DS":1,"FC":1,"SG":1},"apelido":"Tinga","foto":"https://s.sde.globo.com/media/person_role/2024/02/28/photo_FORMATO_vAKLb1d.png","pontuacao":5.9,"posicao_id":2,"clube_id":356,"entrou_em_campo":true},"82766":{"scout":{"FS":1,"I":1},"apelido":"Wellington Rato","foto":"https://s.sde.globo.com/media/person_role/2024/03/01/photo_FORMATO_NhIGhAv.png","pontuacao":0.4,"posicao_id":4,"clube_id":276,"entrou_em_campo":true},"83257":{"scout":{},"apelido":"Gabriel","foto":"https://s.sde.globo.com/media/person_role/2024/02/26/photo_FORMATO_EM6z7aN.png","pontuacao":0,"posicao_id":5,"clube_id":262,"entrou_em_campo":true},"83528":{"scout":{},"apelido":"Léo Pereira","foto":"https://s.sde.globo.com/media/person_role/2024/02/26/photo_FORMATO_rrGsWJ1.png","pontuacao":0,"posicao_id":3,"clube_id":262,"entrou_em_campo":true},"83817":{"scout":{"DS":1,"FC":1,"FD":1},"apelido":"Clayson","foto":"https://s.sde.globo.com/media/person_role/2024/02/29/photo_FORMATO_eqdux0f.png","pontuacao":2.1,"posicao_id":5,"clube_id":1371,"entrou_em_campo":true},"84266":{"scout":{"GS":1},"apelido":"Alisson","foto":"https://s.sde.globo.com/media/person_role/2024/02/28/photo_FORMATO_Ea5KMU8.png","pontuacao":-1,"posicao_id":1,"clube_id":288,"entrou_em_campo":true},"84428":{"scout":{"DS":1},"apelido":"Fernando Sobral","foto":"https://s.sde.globo.com/media/person_role/2024/02/29/photo_FORMATO_dW9VacB.png","pontuacao":1.2,"posicao_id":4,"clube_id":1371,"entrou_em_campo":true},"84674":{"scout":{"DS":1,"FF":2,"FS":1,"I":2},"apelido":"Lucas Evangelista","foto":"https://s.sde.globo.com/media/person_role/2024/01/03/photo_FORMATO_gMVR2lN.png","pontuacao":3.1,"posicao_id":4,"clube_id":280,"entrou_em_campo":true},"85004":{"scout":{"DE":1,"DS":1,"GS":2},"apelido":"Marcos Felipe","foto":"https://s.sde.globo.com/media/person_role/2024/02/29/photo_FORMATO_JDJmU6R.png","pontuacao":0.2,"posicao_id":1,"clube_id":265,"entrou_em_campo":true},"85034":{"scout":{"DS":1,"FC":2,"FS":2},"apelido":"Óscar Romero","foto":"https://s.sde.globo.com/media/person_role/2024/04/20/photo_FORMATO_oSZD8nT.png","pontuacao":1.6,"posicao_id":4,"clube_id":263,"entrou_em_campo":true},"85277":{"scout":{"DS":3,"FC":1,"FF":1},"apelido":"Damián Suárez","foto":"https://s.sde.globo.com/media/person_role/2024/04/20/photo_FORMATO_DpJN07P.png","pontuacao":4.1,"posicao_id":2,"clube_id":263,"entrou_em_campo":true},"85465":{"scout":{"CA":1,"FC":1},"apelido":"Alex Santana","foto":"https://s.sde.globo.com/media/person_role/2024/02/28/photo_FORMATO.png","pontuacao":-1.3,"posicao_id":4,"clube_id":293,"entrou_em_campo":true},"85626":{"scout":{"FC":1,"FS":1,"I":1},"apelido":"Léo","foto":"https://s.sde.globo.com/media/person_role/2024/03/04/photo_FORMATO_EPoR3bv.png","pontuacao":0.1,"posicao_id":3,"clube_id":267,"entrou_em_campo":true},"85931":{"scout":{"DS":3,"FS":2},"apelido":"Hyoran","foto":"https://s.sde.globo.com/media/person_role/2024/02/29/photo_FORMATO_7KxaYiF.png","pontuacao":4.6,"posicao_id":4,"clube_id":285,"entrou_em_campo":true},"86292":{"scout":{"CA":1,"FC":4,"FD":2},"apelido":"Bolasie","foto":"https://s.sde.globo.com/media/person_role/2024/03/20/photo_FORMATO_r97hBeS.png","pontuacao":0.2,"posicao_id":5,"clube_id":288,"entrou_em_campo":true},"86410":{"scout":{"CV":1,"DS":2,"FC":4,"FS":2},"apelido":"Victor Luis","foto":"https://s.sde.globo.com/media/person_role/2024/03/04/photo_FORMATO_C2XW4GI.png","pontuacao":-0.8,"posicao_id":2,"clube_id":267,"entrou_em_campo":true},"86485":{"scout":{},"apelido":"Keno","foto":"https://s.sde.globo.com/media/person_role/2024/04/09/photo_FORMATO_EdYl0O3.png","pontuacao":0,"posicao_id":5,"clube_id":266,"entrou_em_campo":true},"86508":{"scout":{"DE":2,"FS":1,"GS":1},"apelido":"Jandrei","foto":"https://s.sde.globo.com/media/person_role/2024/03/01/photo_FORMATO_FD4URNn.png","pontuacao":1.5,"posicao_id":1,"clube_id":276,"entrou_em_campo":true},"86684":{"scout":{"DS":3,"FC":1,"I":1},"apelido":"Rodrigo","foto":"https://s.sde.globo.com/media/person_role/2024/01/16/photo_FORMATO_fIUc997.png","pontuacao":3.2,"posicao_id":3,"clube_id":288,"entrou_em_campo":true},"86686":{"scout":{"FF":1,"FS":1},"apelido":"Tchê Tchê","foto":"https://s.sde.globo.com/media/person_role/2024/04/20/photo_FORMATO_DbXXPxM.png","pontuacao":1.3,"posicao_id":4,"clube_id":263,"entrou_em_campo":true},"86713":{"scout":{"DS":4},"apelido":"Jonathan","foto":"https://s.sde.globo.com/media/person_role/2024/01/16/photo_FORMATO_9loGKby.png","pontuacao":4.8,"posicao_id":2,"clube_id":288,"entrou_em_campo":true},"86757":{"scout":{"FC":1,"FF":1,"FS":2},"apelido":"Everton","foto":"https://s.sde.globo.com/media/person_role/2024/04/08/photo_FORMATO_JoKRQsF.png","pontuacao":1.5,"posicao_id":5,"clube_id":262,"entrou_em_campo":true},"86777":{"scout":{"DS":1,"FC":1,"FS":1},"apelido":"Danilo Barbosa","foto":"https://s.sde.globo.com/media/person_role/2024/04/20/photo_FORMATO_p79ATUg.png","pontuacao":1.4,"posicao_id":4,"clube_id":263,"entrou_em_campo":true},"86859":{"scout":{"DS":1,"FC":1},"apelido":"José Welison","foto":"https://s.sde.globo.com/media/person_role/2024/02/28/photo_FORMATO_QbOqp5G.png","pontuacao":0.9,"posicao_id":4,"clube_id":356,"entrou_em_campo":true},"87008":{"scout":{"DE":3,"GS":2},"apelido":"Léo Jardim","foto":"https://s.sde.globo.com/media/person_role/2024/03/04/photo_FORMATO_goyzWhz.png","pontuacao":1,"posicao_id":1,"clube_id":267,"entrou_em_campo":true},"87009":{"scout":{"FS":1},"apelido":"Nathan","foto":"https://s.sde.globo.com/media/person_role/2024/03/11/photo_FORMATO_UqG87oy.png","pontuacao":0.5,"posicao_id":4,"clube_id":284,"entrou_em_campo":true},"87225":{"scout":{"DS":2,"FC":3},"apelido":"Pedro Henrique","foto":"https://s.sde.globo.com/media/person_role/2024/04/24/photo_FORMATO_oxcf1Uy.png","pontuacao":1.5,"posicao_id":3,"clube_id":280,"entrou_em_campo":true},"87242":{"scout":{},"apelido":"Carlos de Pena","foto":"https://s.sde.globo.com/media/person_role/2024/04/11/photo_FORMATO_fnqPxDu.png","pontuacao":0,"posicao_id":4,"clube_id":265,"entrou_em_campo":true},"87391":{"scout":{"DS":2,"FC":1,"FS":2},"apelido":"Allano","foto":"https://s.sde.globo.com/media/person_role/2024/04/22/photo_FORMATO_4fbfMIP.png","pontuacao":3.1,"posicao_id":5,"clube_id":288,"entrou_em_campo":true},"87470":{"scout":{"FF":1},"apelido":"Thaciano","foto":"https://s.sde.globo.com/media/person_role/2024/02/15/photo_FORMATO_wgwd4Ze.png","pontuacao":0.8,"posicao_id":4,"clube_id":265,"entrou_em_campo":true},"87603":{"scout":{"CA":1},"apelido":"Mateus Pasinato","foto":"https://s.sde.globo.com/media/person_role/2024/02/29/photo_FORMATO_5YNRqaD.png","pontuacao":-1,"posicao_id":1,"clube_id":1371,"entrou_em_campo":false},"87660":{"scout":{"CA":1,"FC":4,"FS":1},"apelido":"Galdames","foto":"https://s.sde.globo.com/media/person_role/2024/03/04/photo_FORMATO_8l71w1x.png","pontuacao":-1.7,"posicao_id":4,"clube_id":267,"entrou_em_campo":true},"87999":{"scout":{"DS":2,"FD":1,"FS":3,"G":1},"apelido":"Gustavo Scarpa","foto":"https://s.sde.globo.com/media/person_role/2024/03/06/photo_FORMATO_UXqyPlk.png","pontuacao":13.1,"posicao_id":4,"clube_id":282,"entrou_em_campo":true},"88033":{"scout":{"DS":1,"FC":1,"FS":1,"SG":1},"apelido":"Alan Empereur","foto":"https://s.sde.globo.com/media/person_role/2024/02/29/photo_FORMATO_yJZY7yN.png","pontuacao":6.4,"posicao_id":3,"clube_id":1371,"entrou_em_campo":true},"88393":{"scout":{"FF":1,"FS":1},"apelido":"Ayrton Lucas","foto":"https://s.sde.globo.com/media/person_role/2024/04/09/photo_FORMATO_vtzXktM.png","pontuacao":1.3,"posicao_id":2,"clube_id":262,"entrou_em_campo":true},"89141":{"scout":{"V":1},"apelido":"Petit","foto":"https://s.sde.globo.com/media/person_role/2024/05/06/photo_FORMATO_dWuxEhT.png","pontuacao":7.97,"posicao_id":6,"clube_id":1371,"entrou_em_campo":true},"89224":{"scout":{},"apelido":"Barreto","foto":"https://s.sde.globo.com/media/person_role/2024/02/28/photo_FORMATO_ppF3oM9.png","pontuacao":0,"posicao_id":4,"clube_id":288,"entrou_em_campo":true},"89256":{"scout":{"A":1,"DS":1,"FC":1,"FS":2,"G":1},"apelido":"Gerson","foto":"https://s.sde.globo.com/media/person_role/2024/02/26/photo_FORMATO_mBAg0JY.png","pontuacao":14.9,"posicao_id":4,"clube_id":262,"entrou_em_campo":true},"89273":{"scout":{"DS":1,"FF":1,"FS":1},"apelido":"João Pedro","foto":"https://s.sde.globo.com/media/person_role/2024/03/11/photo_FORMATO_yq877xk.png","pontuacao":2.5,"posicao_id":2,"clube_id":284,"entrou_em_campo":true},"89275":{"scout":{"DS":5,"FC":2,"G":2,"SG":1},"apelido":"William","foto":"https://s.sde.globo.com/media/person_role/2024/03/02/photo_FORMATO_Wno5RKV.png","pontuacao":26.4,"posicao_id":2,"clube_id":283,"entrou_em_campo":true},"89467":{"scout":{},"apelido":"Erick","foto":"https://s.sde.globo.com/media/person_role/2024/03/11/photo_FORMATO_GS948NH.png","pontuacao":0,"posicao_id":5,"clube_id":286,"entrou_em_campo":true},"89646":{"scout":{"DS":1,"FC":1},"apelido":"Rodrigo Andrade","foto":"https://s.sde.globo.com/media/person_role/2024/04/12/photo_FORMATO_j4J1Kog.png","pontuacao":0.9,"posicao_id":4,"clube_id":287,"entrou_em_campo":true},"89840":{"scout":{"FC":1,"FF":1,"FS":4,"I":1},"apelido":"Calleri","foto":"https://s.sde.globo.com/media/person_role/2024/03/01/photo_FORMATO_hF89kWc.png","pontuacao":2.4,"posicao_id":5,"clube_id":276,"entrou_em_campo":true},"89846":{"scout":{"FS":3},"apelido":"Cristaldo","foto":"https://s.sde.globo.com/media/person_role/2024/03/11/photo_FORMATO_4i2PnOy.png","pontuacao":1.5,"posicao_id":4,"clube_id":284,"entrou_em_campo":true},"89883":{"scout":{"FS":1},"apelido":"Dodi","foto":"https://s.sde.globo.com/media/person_role/2024/03/11/photo_FORMATO_SoQQafa.png","pontuacao":0.5,"posicao_id":4,"clube_id":284,"entrou_em_campo":true},"90285":{"scout":{"DS":1,"FF":1,"FS":1},"apelido":"Bruno Henrique","foto":"https://s.sde.globo.com/media/person_role/2024/02/26/photo_FORMATO_JiNgXjg.png","pontuacao":2.5,"posicao_id":5,"clube_id":262,"entrou_em_campo":true},"90309":{"scout":{},"apelido":"David","foto":"https://s.sde.globo.com/media/person_role/2024/03/04/photo_FORMATO_4eK3iOa.png","pontuacao":0,"posicao_id":5,"clube_id":267,"entrou_em_campo":true},"90449":{"scout":{"FC":1},"apelido":"Rezende","foto":"https://s.sde.globo.com/media/person_role/2024/02/29/photo_FORMATO_0kSZPcN.png","pontuacao":-0.3,"posicao_id":4,"clube_id":265,"entrou_em_campo":true},"90588":{"scout":{"DS":2,"FC":1,"FS":2},"apelido":"Caíque","foto":"https://s.sde.globo.com/media/person_role/2024/03/11/photo_FORMATO_RJHB8O8.png","pontuacao":3.1,"posicao_id":4,"clube_id":286,"entrou_em_campo":true},"90634":{"scout":{"DS":3,"FC":3},"apelido":"Lucas Mineiro","foto":"https://s.sde.globo.com/media/person_role/2024/02/29/photo_FORMATO_xH8ilrc.png","pontuacao":2.7,"posicao_id":4,"clube_id":1371,"entrou_em_campo":true},"90703":{"scout":{"A":1,"FD":1,"FF":1,"FS":3,"G":1},"apelido":"Matheuzinho","foto":"https://s.sde.globo.com/media/person_role/2024/04/12/photo_FORMATO_oRcCuAx.png","pontuacao":16.5,"posicao_id":4,"clube_id":287,"entrou_em_campo":true},"90715":{"scout":{"DS":1,"FF":1,"GS":1,"I":1},"apelido":"Luiz Fernando","foto":"https://s.sde.globo.com/media/person_role/2024/02/28/photo_FORMATO_TFNlZWH.png","pontuacao":0.9,"posicao_id":5,"clube_id":373,"entrou_em_campo":true},"90943":{"scout":{"DS":2,"FS":2,"SG":1},"apelido":"Zé Marcos","foto":"https://s.sde.globo.com/media/person_role/2024/03/11/photo_FORMATO_s0j6JVw.png","pontuacao":8.4,"posicao_id":3,"clube_id":286,"entrou_em_campo":true},"90947":{"scout":{"DS":1,"SG":1},"apelido":"Cardona","foto":"https://s.sde.globo.com/media/person_role/2024/02/28/photo_FORMATO_YucaBOt.png","pontuacao":6.2,"posicao_id":3,"clube_id":356,"entrou_em_campo":true},"91101":{"scout":{"CV":1,"DE":4,"FC":1,"FS":1,"GS":1},"apelido":"Ronaldo","foto":"https://s.sde.globo.com/media/person_role/2024/02/28/photo_FORMATO_AaiyHtB.png","pontuacao":0.2,"posicao_id":1,"clube_id":373,"entrou_em_campo":true},"91254":{"scout":{"FC":1},"apelido":"Carballo","foto":"https://s.sde.globo.com/media/person_role/2024/03/11/photo_FORMATO_w5Qzw1m.png","pontuacao":-0.3,"posicao_id":4,"clube_id":284,"entrou_em_campo":true},"91573":{"scout":{"DS":3},"apelido":"Arboleda","foto":"https://s.sde.globo.com/media/person_role/2024/05/07/photo_FORMATO_4juynn8.png","pontuacao":3.6,"posicao_id":3,"clube_id":276,"entrou_em_campo":true},"91607":{"scout":{"DS":1,"FD":1,"FF":2,"FS":2,"G":1,"I":2},"apelido":"Rony","foto":"https://s.sde.globo.com/media/person_role/2024/02/27/photo_FORMATO_j8iPskd.png","pontuacao":12.8,"posicao_id":5,"clube_id":275,"entrou_em_campo":true},"91706":{"scout":{"DS":1,"FC":3,"FD":1,"FF":1,"SG":1},"apelido":"Marlon","foto":"https://s.sde.globo.com/media/person_role/2024/03/02/photo_FORMATO_6dy9M0T.png","pontuacao":7.3,"posicao_id":2,"clube_id":283,"entrou_em_campo":true},"91866":{"scout":{"DS":1,"FF":1,"FS":1,"I":1,"SG":1},"apelido":"Zé Ivaldo","foto":"https://s.sde.globo.com/media/person_role/2024/03/02/photo_FORMATO_XkfvN4h.png","pontuacao":7.4,"posicao_id":3,"clube_id":283,"entrou_em_campo":true},"91908":{"scout":{"FS":2},"apelido":"Pavón","foto":"https://s.sde.globo.com/media/person_role/2024/03/11/photo_FORMATO_cVczRJH.png","pontuacao":1,"posicao_id":5,"clube_id":284,"entrou_em_campo":true},"92149":{"scout":{"FC":1,"FS":1,"I":2},"apelido":"Alario","foto":"https://s.sde.globo.com/media/person_role/2024/03/01/photo_FORMATO_5Z61ABy.png","pontuacao":0,"posicao_id":5,"clube_id":285,"entrou_em_campo":true},"92180":{"scout":{},"apelido":"Jair Ventura","foto":"https://s.sde.globo.com/media/person_role/2018/09/06/d1103130500ec84fd8e37f1a20c60e1a_FORMATO.png","pontuacao":3.18,"posicao_id":6,"clube_id":373,"entrou_em_campo":true},"92237":{"scout":{"CA":1,"DS":2,"FD":1,"FS":2,"FT":1,"PC":1},"apelido":"Rodrigo Ely","foto":"https://s.sde.globo.com/media/person_role/2024/03/11/photo_FORMATO_RubzI83.png","pontuacao":5.6,"posicao_id":3,"clube_id":284,"entrou_em_campo":true},"93478":{"scout":{"DS":1,"FC":3,"FD":1,"FS":2},"apelido":"Wanderson","foto":"https://s.sde.globo.com/media/person_role/2024/03/01/photo_FORMATO_ntpiKUS.png","pontuacao":2.5,"posicao_id":5,"clube_id":285,"entrou_em_campo":true},"93702":{"scout":{"DS":1,"FS":1,"SG":1},"apelido":"Gabriel Inocêncio","foto":"https://s.sde.globo.com/media/person_role/2024/04/10/photo_FORMATO_P3G6ct6.png","pontuacao":6.7,"posicao_id":2,"clube_id":286,"entrou_em_campo":true},"93716":{"scout":{"DS":1},"apelido":"Paulo Henrique","foto":"https://s.sde.globo.com/media/person_role/2024/03/04/photo_FORMATO_9IoUUlz.png","pontuacao":1.2,"posicao_id":2,"clube_id":267,"entrou_em_campo":true},"93790":{"scout":{},"apelido":"Marlon Freitas","foto":"https://s.sde.globo.com/media/person_role/2024/04/20/photo_FORMATO_IWdTjkg.png","pontuacao":0,"posicao_id":4,"clube_id":263,"entrou_em_campo":true},"93882":{"scout":{"DE":5,"GS":2},"apelido":"Cleiton","foto":"https://s.sde.globo.com/media/person_role/2024/01/03/photo_FORMATO_Ri9cYDm.png","pontuacao":3,"posicao_id":1,"clube_id":280,"entrou_em_campo":true},"93886":{"scout":{"FF":1},"apelido":"Matheusinho","foto":"https://s.sde.globo.com/media/person_role/2024/04/09/photo_FORMATO_PCw311H.png","pontuacao":0.8,"posicao_id":4,"clube_id":288,"entrou_em_campo":true},"93988":{"scout":{"FC":1,"FF":1,"I":1},"apelido":"Breno Lopes","foto":"https://s.sde.globo.com/media/person_role/2024/04/19/photo_FORMATO_XhXbbVU.png","pontuacao":0.4,"posicao_id":5,"clube_id":356,"entrou_em_campo":true},"94044":{"scout":{"DE":5,"GS":1},"apelido":"John Victor","foto":"https://s.sde.globo.com/media/person_role/2024/04/20/photo_FORMATO_5TQNQjS.png","pontuacao":4,"posicao_id":1,"clube_id":263,"entrou_em_campo":true},"94067":{"scout":{"DS":2,"FD":1,"FS":2,"G":1},"apelido":"Matheus Fernandes","foto":"https://s.sde.globo.com/media/person_role/2024/01/03/photo_FORMATO_sgQrNPa.png","pontuacao":12.6,"posicao_id":4,"clube_id":280,"entrou_em_campo":true},"94509":{"scout":{"DS":2,"FC":1,"FF":4,"FS":2,"G":1},"apelido":"Raphael Veiga","foto":"https://s.sde.globo.com/media/person_role/2024/02/27/photo_FORMATO_XOXiO3C.png","pontuacao":14.3,"posicao_id":4,"clube_id":275,"entrou_em_campo":true},"94583":{"scout":{"A":1,"DS":2,"FC":1,"FF":1},"apelido":"Pedro","foto":"https://s.sde.globo.com/media/person_role/2024/02/26/photo_FORMATO_xrhSS2w.png","pontuacao":7.9,"posicao_id":5,"clube_id":262,"entrou_em_campo":true},"94845":{"scout":{"DS":1,"FC":2,"FS":1},"apelido":"Battaglia","foto":"https://s.sde.globo.com/media/person_role/2023/04/13/photo_FORMATO_XVs5pqz.png","pontuacao":1.1,"posicao_id":4,"clube_id":282,"entrou_em_campo":true},"94853":{"scout":{"V":1},"apelido":"Eduardo Coudet","foto":"https://s.sde.globo.com/media/person_role/2024/02/29/photo_FORMATO_apsV9qH.png","pontuacao":8.02,"posicao_id":6,"clube_id":285,"entrou_em_campo":true},"94968":{"scout":{"DS":5,"FC":1,"FS":3},"apelido":"Juninho Capixaba","foto":"https://s.sde.globo.com/media/person_role/2024/01/03/photo_FORMATO_U4Lwrth.png","pontuacao":7.2,"posicao_id":2,"clube_id":280,"entrou_em_campo":true},"95131":{"scout":{"FS":1},"apelido":"Gabriel Taliari","foto":"https://s.sde.globo.com/media/person_role/2024/03/11/photo_FORMATO_vGTDrZr.png","pontuacao":0.5,"posicao_id":5,"clube_id":286,"entrou_em_campo":true},"95464":{"scout":{"DS":3,"FC":1},"apelido":"Gregore","foto":"https://s.sde.globo.com/media/person_role/2024/03/12/photo_FORMATO_OoYMXid.png","pontuacao":3.3,"posicao_id":4,"clube_id":263,"entrou_em_campo":true},"95466":{"scout":{"FS":2},"apelido":"Igor Vinícius","foto":"https://s.sde.globo.com/media/person_role/2024/03/01/photo_FORMATO_DKQOGT2.png","pontuacao":1,"posicao_id":2,"clube_id":276,"entrou_em_campo":true},"95556":{"scout":{"DS":1,"FC":2},"apelido":"Raniele","foto":"https://s.sde.globo.com/media/person_role/2024/02/27/photo_FORMATO_wftQgQv.png","pontuacao":0.6,"posicao_id":4,"clube_id":264,"entrou_em_campo":true},"95662":{"scout":{"DS":1},"apelido":"Lucas Kal","foto":"https://s.sde.globo.com/media/person_role/2024/03/12/photo_FORMATO_Ho8rTXl.png","pontuacao":1.2,"posicao_id":4,"clube_id":373,"entrou_em_campo":true},"95738":{"scout":{"DS":1,"FS":1,"G":1},"apelido":"Trauco","foto":"https://s.sde.globo.com/media/person_role/2024/03/12/photo_FORMATO_38OPKZz.png","pontuacao":9.7,"posicao_id":2,"clube_id":288,"entrou_em_campo":true},"95878":{"scout":{"FS":1},"apelido":"Tobias Figueiredo","foto":"https://s.sde.globo.com/media/person_role/2024/03/07/photo_FORMATO_GTVYOSI.png","pontuacao":0.5,"posicao_id":3,"clube_id":288,"entrou_em_campo":true},"96089":{"scout":{"CA":1,"DS":1,"FC":4,"FS":2},"apelido":"Machado","foto":"https://s.sde.globo.com/media/person_role/2024/03/01/photo_FORMATO_frORMmM.png","pontuacao":0,"posicao_id":4,"clube_id":283,"entrou_em_campo":true},"96340":{"scout":{"DS":3,"FC":3,"FD":1,"FF":1,"FS":3},"apelido":"Lima","foto":"https://s.sde.globo.com/media/person_role/2024/04/09/photo_FORMATO_Lwuhu7n.png","pontuacao":6.2,"posicao_id":4,"clube_id":266,"entrou_em_campo":true},"96610":{"scout":{"CA":1,"DS":1,"FC":1,"FF":1,"FS":4,"I":1},"apelido":"Matheus Pereira","foto":"https://s.sde.globo.com/media/person_role/2024/03/02/photo_FORMATO_tZZNLQo.png","pontuacao":2.6,"posicao_id":4,"clube_id":283,"entrou_em_campo":true},"96652":{"scout":{"DS":1},"apelido":"Allan","foto":"https://s.sde.globo.com/media/person_role/2024/02/26/photo_FORMATO_j7yMylW.png","pontuacao":1.2,"posicao_id":4,"clube_id":262,"entrou_em_campo":true},"96673":{"scout":{},"apelido":"Gabriel Milito","foto":"https://s.sde.globo.com/media/person_role/2024/03/24/photo_FORMATO.png","pontuacao":4.47,"posicao_id":6,"clube_id":282,"entrou_em_campo":true},"96678":{"scout":{"DS":2,"FC":1,"FS":1,"SG":1},"apelido":"Bustos","foto":"https://s.sde.globo.com/media/person_role/2024/02/29/photo_FORMATO_4JN6eBb.png","pontuacao":7.6,"posicao_id":2,"clube_id":285,"entrou_em_campo":true},"96725":{"scout":{"DS":4,"FC":2,"FS":3},"apelido":"Saravia","foto":"https://s.sde.globo.com/media/person_role/2023/03/31/photo_FORMATO_HmHq0Tu.png","pontuacao":5.7,"posicao_id":2,"clube_id":282,"entrou_em_campo":true},"96966":{"scout":{"DS":1},"apelido":"Arthur Gomes","foto":"https://s.sde.globo.com/media/person_role/2024/03/01/photo_FORMATO_0C3TGei.png","pontuacao":1.2,"posicao_id":5,"clube_id":283,"entrou_em_campo":true},"97341":{"scout":{},"apelido":"Rogério Ceni","foto":"https://s.sde.globo.com/media/person_role/2022/03/01/e6fac1f227854170a80b2cf3234bfa1d_FORMATO.png","pontuacao":2.63,"posicao_id":6,"clube_id":265,"entrou_em_campo":true},"97450":{"scout":{},"apelido":"Gustavo Mosquito","foto":"https://s.sde.globo.com/media/person_role/2024/02/27/photo_FORMATO_6NQENP4.png","pontuacao":0,"posicao_id":5,"clube_id":264,"entrou_em_campo":true},"97520":{"scout":{"A":1,"DS":1,"FF":2},"apelido":"Shaylon","foto":"https://s.sde.globo.com/media/person_role/2024/02/28/photo_FORMATO_6COfCnm.png","pontuacao":7.8,"posicao_id":4,"clube_id":373,"entrou_em_campo":true},"97547":{"scout":{},"apelido":"Estupiñán","foto":"https://s.sde.globo.com/media/person_role/2024/02/14/photo_FORMATO.png","pontuacao":0,"posicao_id":5,"clube_id":265,"entrou_em_campo":true},"97640":{"scout":{"DS":1,"FC":1,"G":1},"apelido":"Eryc Castillo","foto":"https://s.sde.globo.com/media/person_role/2024/04/12/photo_FORMATO_xuxbOxr.png","pontuacao":8.9,"posicao_id":5,"clube_id":287,"entrou_em_campo":true},"97653":{"scout":{"FC":1},"apelido":"Murilo","foto":"https://s.sde.globo.com/media/person_role/2024/02/27/photo_FORMATO_YJUCJBH.png","pontuacao":-0.3,"posicao_id":3,"clube_id":275,"entrou_em_campo":true},"97867":{"scout":{"CA":1,"DS":3,"FC":3},"apelido":"Léo Ortiz","foto":"https://s.sde.globo.com/media/person_role/2024/05/13/photo_FORMATO_Nw5qKTd.png","pontuacao":1.7,"posicao_id":3,"clube_id":262,"entrou_em_campo":true},"98022":{"scout":{"CA":1,"DS":2,"FC":1,"FD":1,"FS":1},"apelido":"Erick","foto":"https://s.sde.globo.com/media/person_role/2024/03/01/photo_FORMATO_PzrcPox.png","pontuacao":2.8,"posicao_id":4,"clube_id":293,"entrou_em_campo":true},"98225":{"scout":{},"apelido":"Pedro Raul","foto":"https://s.sde.globo.com/media/person_role/2024/02/27/photo_FORMATO_btuS15d.png","pontuacao":0,"posicao_id":5,"clube_id":264,"entrou_em_campo":true},"98280":{"scout":{"DS":2,"FC":1,"FF":1,"G":1},"apelido":"Bastos","foto":"https://s.sde.globo.com/media/person_role/2024/04/20/photo_FORMATO_sq29S9f.png","pontuacao":10.9,"posicao_id":3,"clube_id":263,"entrou_em_campo":true},"98484":{"scout":{"DS":1,"FS":2},"apelido":"Kanu","foto":"https://s.sde.globo.com/media/person_role/2024/02/29/photo_FORMATO_OKP0vwQ.png","pontuacao":2.2,"posicao_id":3,"clube_id":265,"entrou_em_campo":true},"98517":{"scout":{"A":1,"CA":1,"DS":1,"FC":4,"FD":1,"FF":2},"apelido":"Jean Lucas","foto":"https://s.sde.globo.com/media/person_role/2024/02/29/photo_FORMATO_Lb03bwo.png","pontuacao":6.8,"posicao_id":4,"clube_id":265,"entrou_em_campo":true},"98706":{"scout":{"DS":1,"FS":1,"PS":1},"apelido":"Pedrinho","foto":"https://s.sde.globo.com/media/person_role/2023/03/31/photo_FORMATO_QTjI0Vv.png","pontuacao":2.7,"posicao_id":4,"clube_id":282,"entrou_em_campo":true},"98909":{"scout":{"A":1,"DS":1,"FD":2,"FS":1},"apelido":"Cuello","foto":"https://s.sde.globo.com/media/person_role/2024/03/01/photo_FORMATO_JnDE8PH.png","pontuacao":9.1,"posicao_id":5,"clube_id":293,"entrou_em_campo":true},"99267":{"scout":{"DS":2,"FD":1},"apelido":"Pochettino","foto":"https://s.sde.globo.com/media/person_role/2024/02/28/photo_FORMATO_up62cTi.png","pontuacao":3.6,"posicao_id":4,"clube_id":356,"entrou_em_campo":true},"99366":{"scout":{},"apelido":"Luis Zubeldía","foto":"https://s.sde.globo.com/media/person_role/2024/04/20/photo_FORMATO_1Msj2GU.png","pontuacao":2.91,"posicao_id":6,"clube_id":276,"entrou_em_campo":true},"99440":{"scout":{"FC":1,"FF":2},"apelido":"Baralhas","foto":"https://s.sde.globo.com/media/person_role/2024/02/28/photo_FORMATO_5FJVKbT.png","pontuacao":1.3,"posicao_id":4,"clube_id":373,"entrou_em_campo":true},"99552":{"scout":{"DE":2,"GS":1},"apelido":"Rossi","foto":"https://s.sde.globo.com/media/person_role/2024/02/26/photo_FORMATO_sM4o3AF.png","pontuacao":1,"posicao_id":1,"clube_id":262,"entrou_em_campo":true},"99623":{"scout":{"DS":1,"FC":1,"FF":3,"FS":3,"G":1},"apelido":"Guilherme Romão","foto":"https://s.sde.globo.com/media/person_role/2024/02/28/photo_FORMATO_uJhNaxu.png","pontuacao":12.8,"posicao_id":2,"clube_id":373,"entrou_em_campo":true}},"clubes":{"1371":{"escudos":{"60x60":"https://s.sde.globo.com/media/organizations/2014/04/16/cuiaba65.png","45x45":"https://s.sde.globo.com/media/organizations/2014/04/16/cuiaba45.png","30x30":"https://s.sde.globo.com/media/organizations/2014/04/16/cuiaba30_.png"},"nome":"Cuiabá","abreviacao":"CUI","slug":"cuiaba","apelido":"Dourado","nome_fantasia":"Cuiabá","id":1371,"url_editoria":"https://ge.globo.com/mt/futebol/times/cuiaba/"},"262":{"escudos":{"60x60":"https://s.sde.globo.com/media/organizations/2018/04/09/Flamengo-65.png","45x45":"https://s.sde.globo.com/media/organizations/2018/04/09/Flamengo-45.png","30x30":"https://s.sde.globo.com/media/organizations/2018/04/09/Flamengo-30.png"},"nome":"Flamengo","abreviacao":"FLA","slug":"flamengo","apelido":"Mengão","nome_fantasia":"Flamengo","id":262,"url_editoria":"https://ge.globo.com/futebol/times/flamengo/"},"263":{"escudos":{"60x60":"https://s.sde.globo.com/media/organizations/2019/02/04/botafogo-65.png","45x45":"https://s.sde.globo.com/media/organizations/2019/02/04/botafogo-45.png","30x30":"https://s.sde.globo.com/media/organizations/2019/02/04/botafogo-30.png"},"nome":"Botafogo","abreviacao":"BOT","slug":"botafogo","apelido":"Glorioso","nome_fantasia":"Botafogo","id":263,"url_editoria":"https://ge.globo.com/futebol/times/botafogo/"},"264":{"escudos":{"60x60":"https://s.sde.globo.com/media/organizations/2019/09/30/Corinthians_65.png","45x45":"https://s.sde.globo.com/media/organizations/2019/09/30/Corinthians_45.png","30x30":"https://s.sde.globo.com/media/organizations/2019/09/30/Corinthians_30.png"},"nome":"Corinthians","abreviacao":"COR","slug":"corinthians","apelido":"Timão","nome_fantasia":"Corinthians","id":264,"url_editoria":"https://ge.globo.com/futebol/times/corinthians/"},"265":{"escudos":{"60x60":"https://s.sde.globo.com/media/organizations/2014/04/14/bahia_60x60.png","45x45":"https://s.sde.globo.com/media/organizations/2014/04/14/bahia_45x45.png","30x30":"https://s.sde.globo.com/media/organizations/2014/04/14/bahia_30x30.png"},"nome":"Bahia","abreviacao":"BAH","slug":"bahia","apelido":"Tricolor de Aço","nome_fantasia":"Bahia","id":265,"url_editoria":"https://ge.globo.com/ba/futebol/times/bahia/"},"266":{"escudos":{"60x60":"https://s.sde.globo.com/media/organizations/2014/04/14/fluminense_60x60.png","45x45":"https://s.sde.globo.com/media/organizations/2014/04/14/fluminense_45x45.png","30x30":"https://s.sde.globo.com/media/organizations/2015/01/12/Fluminense-escudo.png"},"nome":"Fluminense","abreviacao":"FLU","slug":"fluminense","apelido":"Tricolor","nome_fantasia":"Fluminense","id":266,"url_editoria":"https://ge.globo.com/futebol/times/fluminense/"},"267":{"escudos":{"60x60":"https://s.sde.globo.com/media/organizations/2021/09/04/ESCUDO-VASCO-RGB_65px.png","45x45":"https://s.sde.globo.com/media/organizations/2021/09/04/ESCUDO-VASCO-RGB_45px.png","30x30":"https://s.sde.globo.com/media/organizations/2021/09/04/ESCUDO-VASCO-RGB_30px.png"},"nome":"Vasco","abreviacao":"VAS","slug":"vasco","apelido":"Gigante da Colina","nome_fantasia":"Vasco","id":267,"url_editoria":"https://ge.globo.com/futebol/times/vasco/"},"275":{"escudos":{"60x60":"https://s.sde.globo.com/media/organizations/2014/04/14/palmeiras_60x60.png","45x45":"https://s.sde.globo.com/media/organizations/2014/04/14/palmeiras_45x45.png","30x30":"https://s.sde.globo.com/media/organizations/2014/04/14/palmeiras_30x30.png"},"nome":"Palmeiras","abreviacao":"PAL","slug":"palmeiras","apelido":"Verdão","nome_fantasia":"Palmeiras","id":275,"url_editoria":"https://ge.globo.com/futebol/times/palmeiras/"},"276":{"escudos":{"60x60":"https://s.sde.globo.com/media/organizations/2014/04/14/sao_paulo_60x60.png","45x45":"https://s.sde.globo.com/media/organizations/2014/04/14/sao_paulo_45x45.png","30x30":"https://s.sde.globo.com/media/organizations/2014/04/14/sao_paulo_30x30.png"},"nome":"São Paulo","abreviacao":"SAO","slug":"sao-paulo","apelido":"Tricolor","nome_fantasia":"São Paulo","id":276,"url_editoria":"https://ge.globo.com/futebol/times/sao-paulo/"},"280":{"escudos":{"60x60":"https://s.sde.globo.com/media/organizations/2020/01/01/65.png","45x45":"https://s.sde.globo.com/media/organizations/2020/01/01/45.png","30x30":"https://s.sde.globo.com/media/organizations/2020/01/01/30.png"},"nome":"Bragantino","abreviacao":"BGT","slug":"bragantino","apelido":"Massa Bruta","nome_fantasia":"Bragantino","id":280,"url_editoria":"https://ge.globo.com/sp/vale-do-paraiba-regiao/futebol/times/bragantino/"},"282":{"escudos":{"60x60":"https://s.sde.globo.com/media/organizations/2017/11/23/Atletico-Mineiro-escudo65px.png","45x45":"https://s.sde.globo.com/media/organizations/2017/11/23/Atletico-Mineiro-escudo45px.png","30x30":"https://s.sde.globo.com/media/organizations/2017/11/23/Atletico-Mineiro-escudo30px.png"},"nome":"Atlético-MG","abreviacao":"CAM","slug":"atletico-mg","apelido":"Galo","nome_fantasia":"Atlético-MG","id":282,"url_editoria":"https://ge.globo.com/futebol/times/atletico-mg/"},"283":{"escudos":{"60x60":"https://s.sde.globo.com/media/organizations/2021/02/13/65_cruzeiro-2021.png","45x45":"https://s.sde.globo.com/media/organizations/2021/02/13/45_cruzeiro-2021.png","30x30":"https://s.sde.globo.com/media/organizations/2021/02/13/30_cruzeiro-2021.png"},"nome":"Cruzeiro","abreviacao":"CRU","slug":"cruzeiro","apelido":"Raposa","nome_fantasia":"Cruzeiro","id":283,"url_editoria":"https://ge.globo.com/futebol/times/cruzeiro/"},"284":{"escudos":{"60x60":"https://s.sde.globo.com/media/organizations/2014/04/14/gremio_60x60.png","45x45":"https://s.sde.globo.com/media/organizations/2014/04/14/gremio_45x45.png","30x30":"https://s.sde.globo.com/media/organizations/2014/04/14/gremio_30x30.png"},"nome":"Grêmio","abreviacao":"GRE","slug":"gremio","apelido":"Imortal","nome_fantasia":"Grêmio","id":284,"url_editoria":"https://ge.globo.com/rs/futebol/times/gremio/"},"285":{"escudos":{"60x60":"https://s.sde.globo.com/media/organizations/2016/05/03/inter65.png","45x45":"https://s.sde.globo.com/media/organizations/2016/05/03/inter45.png","30x30":"https://s.sde.globo.com/media/organizations/2016/05/03/inter30.png"},"nome":"Internacional","abreviacao":"INT","slug":"internacional","apelido":"Colorado","nome_fantasia":"Internacional","id":285,"url_editoria":"https://ge.globo.com/rs/futebol/times/internacional/"},"286":{"escudos":{"60x60":"https://s.sde.globo.com/media/organizations/2021/04/29/juventude65.png","45x45":"https://s.sde.globo.com/media/organizations/2021/04/29/juventude45.png","30x30":"https://s.sde.globo.com/media/organizations/2021/04/29/juventude30.png"},"nome":"Juventude","abreviacao":"JUV","slug":"juventude","apelido":"Papo","nome_fantasia":"Juventude","id":286,"url_editoria":"https://ge.globo.com/rs/futebol/times/juventude/"},"287":{"escudos":{"60x60":"https://s.sde.globo.com/media/organizations/2024/04/09/escudo-vitoria-65x65-69284.png","45x45":"https://s.sde.globo.com/media/organizations/2024/04/09/escudo-vitoria-45x45-69283.png","30x30":"https://s.sde.globo.com/media/organizations/2024/04/09/escudo-vitoria-30x30-69282.png"},"nome":"Vitória","abreviacao":"VIT","slug":"vitoria","apelido":"Vitória","nome_fantasia":"Vitória","id":287,"url_editoria":"https://ge.globo.com/ba/futebol/times/vitoria/"},"288":{"escudos":{"60x60":"https://s.sde.globo.com/media/organizations/2024/03/28/criciuma-65.png","45x45":"https://s.sde.globo.com/media/organizations/2024/03/28/criciuma-45.png","30x30":"https://s.sde.globo.com/media/organizations/2024/03/28/criciuma-30.png"},"nome":"Criciúma","abreviacao":"CRI","slug":"criciuma","apelido":"Tigre","nome_fantasia":"Criciúma","id":288,"url_editoria":"https://ge.globo.com/sc/futebol/times/criciuma/"},"293":{"escudos":{"60x60":"https://s.sde.globo.com/media/organizations/2019/09/09/Athletico-PR-65x65.png","45x45":"https://s.sde.globo.com/media/organizations/2019/09/09/Athletico-PR-45x45.png","30x30":"https://s.sde.globo.com/media/organizations/2019/09/09/Athletico-PR-30x30.png"},"nome":"Athlético-PR","abreviacao":"CAP","slug":"atletico-pr","apelido":"Furacão","nome_fantasia":"Athlético-PR","id":293,"url_editoria":"https://ge.globo.com/pr/futebol/times/athletico-pr/"},"356":{"escudos":{"60x60":"https://s.sde.globo.com/media/organizations/2021/09/19/65_0000_Fortaleza-2021.png","45x45":"https://s.sde.globo.com/media/organizations/2021/09/19/45_0000_Fortaleza-2021.png","30x30":"https://s.sde.globo.com/media/organizations/2021/09/19/30_0000_Fortaleza-2021.png"},"nome":"Fortaleza","abreviacao":"FOR","slug":"fortaleza","apelido":"Leão do Pici","nome_fantasia":"Fortaleza","id":356,"url_editoria":"https://ge.globo.com/ce/futebol/times/fortaleza/"},"373":{"escudos":{"60x60":"https://s.sde.globo.com/media/organizations/2020/07/02/atletico-go-2020-65.png","45x45":"https://s.sde.globo.com/media/organizations/2020/07/02/atletico-go-2020-45.png","30x30":"https://s.sde.globo.com/media/organizations/2020/07/02/atletico-go-2020-30.png"},"nome":"Atlético-GO","abreviacao":"ACG","slug":"atletico-go","apelido":"Dragão","nome_fantasia":"Atlético-GO","id":373,"url_editoria":"https://ge.globo.com/go/futebol/times/atletico-go/"}},"posicoes":{"1":{"id":1,"nome":"Goleiro","abreviacao":"gol"},"2":{"id":2,"nome":"Lateral","abreviacao":"lat"},"3":{"id":3,"nome":"Zagueiro","abreviacao":"zag"},"4":{"id":4,"nome":"Meia","abreviacao":"mei"},"5":{"id":5,"nome":"Atacante","abreviacao":"ata"},"6":{"id":6,"nome":"Técnico","abreviacao":"tec"}},"rodada":10,"total_atletas":337}
